{
  "title": "ویژگی‌های جغرافیایی فارس",
  "location": {
    "province": "فارس",
    "city": "فارس"
  },
  "geographical_features": [
    {
      "name": "گنبدهای نمکی",
      "description": [
        {
          "name": "گنبدهای نمکی",
          "images": [
            "https://newsmedia.tasnimnews.com/Tasnim/Uploaded/Image/1395/09/21/13950921110813219425914.jpg"
          ],
          "description": "گنبدهای نمکی ساختارهای زمین‌شناسی گنبدی‌شکل با هستهٔ مرکزی از نمک هستند که در نواحی جنوبی و شرقی استان، به‌ویژه منطقهٔ لارستان، قرار دارند و اهمیت اقتصادی آنها به‌واسطهٔ وجود مخازن نفت و منابع معدنی مانند پتاسیم، آهن و نمک بسیار بالاست.",
          "vote": [
            {
              "labels": [
                "Acceptable"
              ]
            }
          ]
        }
      ]
    },
    {
      "name": "بیابان‌ها",
      "description": [
        {
          "name": "کویر قطرویه",
          "images": [
            "https://upload.wikimedia.org/wikipedia/commons/a/a9/Map_iran_biotopes_simplified-fr.png"
          ],
          "description": "کویر قطرویه در شرق استان فارس و در محدودهٔ شهرستان نی‌ریز واقع شده و به‌دلیل تبخیر شدید و تجمع نمک بر سطح زمین، چشم‌اندازی کویری و زیستگاهی خشک برای گونه‌های مقاوم به خشکی فراهم می‌آورد.",
          "vote": [
            {
              "labels": [
                "Acceptable"
              ]
            }
          ]
        },
        {
          "name": "بیابان بوانات",
          "images": [],
          "description": "بیابان بوانات در شمال استان فارس، شهرستان بوانات، عرصه‌هایی از شنزارهای شنی است که به دلیل بارش کم، مناظری کویری و خشک را به نمایش می‌گذارد.",
          "vote": [
            {
              "labels": [
                "Acceptable"
              ]
            }
          ]
        },
        {
          "name": "بیابان آباده",
          "images": [
            "https://upload.wikimedia.org/wikipedia/commons/c/cf/Fars_fa.svg"
          ],
          "description": "بیابان آباده در شمال استان فارس و محدودهٔ شهرستان آباده قرار دارد؛ خاک شور و شنزارهای گسترده آن، شرایطی کویری را شکل داده است.",
          "vote": [
            {
              "labels": [
                "Acceptable"
              ]
            }
          ]
        },
        {
          "name": "بیابان لارستان",
          "images": [],
          "description": "بیابان لارستان در جنوب استان فارس، نواحی شهرستان لار واقع است و به‌دلیل تبخیر بالا و بارش کم، مناظری کاملاً بیابانی دارد.",
          "vote": [
            {
              "labels": [
                "Acceptable"
              ]
            }
          ]
        },
        {
          "name": "بیابان لامرد",
          "images": [],
          "description": "بیابان لامرد در نیمهٔ جنوبی استان فارس و شهرستان لامرد گسترده و به‌واسطهٔ پوشش گیاهی بسیار کم و خاک شور، در زمرهٔ نواحی خشک و بایر فارس قرار می‌گیرد.",
          "vote": [
            {
              "labels": [
                "Acceptable"
              ]
            }
          ]
        }
      ]
    },
    {
      "name": "دریاچه‌ها",
      "description": [
        {
          "name": "دریاچه کافتر",
          "images": [
            "https://upload.wikimedia.org/wikipedia/commons/9/99/Iran_-_Fars_-_Eqlid_-_Kaftar_Lake_-_panoramio.jpg"
          ],
          "description": "دریاچهٔ کافتر در شرق استان فارس نزدیک شهرستان نی‌ریز واقع شده و از دریاچه‌های شور دائمی استان است که در اثر تبخیر شدید آب و انباشت نمک ایجاد شده و زیستگاه گونه‌های مقاوم به شوری به شمار می‌رود.",
          "vote": [
            {
              "labels": [
                "Acceptable"
              ]
            }
          ]
        },
        {
          "name": "دریاچه مهارلو",
          "images": [
            "https://upload.wikimedia.org/wikipedia/commons/f/f4/Ecoregion_PA0446.svg"
          ],
          "description": "دریاچه مهارلو در نزدیکی شیراز قرار دارد و به دلیل رنگ صورتی‌اش معروف است. این دریاچه به عنوان یکی از منابع آب شیرین و همچنین زیستگاه پرندگان مهاجر شناخته می‌شود. دریاچه مهارلو به دلیل تبخیر بالا در فصل تابستان، غلظت نمک بالایی دارد که بر تنوع زیستی آن تأثیر می‌گذارد.",
          "vote": [
            {
              "labels": [
                "Acceptable"
              ]
            }
          ]
        },
        {
          "name": "دریاچه پریشان",
          "images": [
            "https://upload.wikimedia.org/wikipedia/commons/thumb/2/28/%D8%AF%D8%B1%D9%8A%D8%A7%DA%86%D9%87_%D9%BE%D8%B1%D9%8A%D8%B4%D8%A7%D9%86_parishan_lake_-_panoramio.jpg/1200px-%D8%AF%D8%B1%D9%8A%D8%A7%DA%86%D9%87_%D9%BE%D8%B1%D9%8A%D8%B4%D8%A7%D9%86_parishan_lake_-_panoramio.jpg"
          ],
          "description": "دریاچه پریشان در شهرستان کازرون واقع شده و به عنوان یکی از دریاچه‌های دائمی استان فارس شناخته می‌شود. این دریاچه به دلیل موقعیت جغرافیایی خاص و تنوع زیستی، مقصدی مناسب برای علاقه‌مندان به پرنده‌نگری و طبیعت‌گردی است.",
          "vote": [
            {
              "labels": [
                "Acceptable"
              ]
            }
          ]
        },
        {
          "name": "دریاچه بختگان",
          "images": [
            "https://upload.wikimedia.org/wikipedia/commons/3/36/Bakhtegan_Lake.jpg"
          ],
          "description": "دریاچه بختگان در استان فارس واقع شده و به عنوان یکی از دریاچه‌های بزرگ و مهم کشور شناخته می‌شود. این دریاچه به دلیل موقعیت جغرافیایی خاص و تنوع زیستی، زیستگاه پرندگان مهاجر و گونه‌های مختلف جانوری است.",
          "vote": [
            {
              "labels": [
                "Acceptable"
              ]
            }
          ]
        },
        {
          "name": "دریاچه نرگس",
          "images": [],
          "description": "دریاچه نرگس در شهرستان نی‌ریز واقع شده و به عنوان یکی از دریاچه‌های زیبا و طبیعی استان فارس شناخته می‌شود. این دریاچه به دلیل تنوع زیستی و زیبایی‌های طبیعی، مقصدی مناسب برای گردشگران و طبیعت‌گردان است.",
          "vote": [
            {
              "labels": [
                "Acceptable"
              ]
            }
          ]
        },
        {
          "name": "دریاچه طشک",
          "images": [
            "https://upload.wikimedia.org/wikipedia/commons/a/af/IranBishapur1.jpg"
          ],
          "description": "دریاچه طشک در شهرستان نی‌ریز واقع شده و به عنوان یکی از دریاچه‌های مهم و طبیعی استان فارس شناخته می‌شود. این دریاچه به دلیل موقعیت جغرافیایی خاص و تنوع زیستی، زیستگاه پرندگان مهاجر و گونه‌های مختلف جانوری است.",
          "vote": [
            {
              "labels": [
                "Acceptable"
              ]
            }
          ]
        },
        {
          "name": "دریاچه قیر",
          "images": [
            "https://upload.wikimedia.org/wikipedia/commons/thumb/d/d8/STAPP_114_La_Brea_Pitch_Lake.jpg/250px-STAPP_114_La_Brea_Pitch_Lake.jpg"
          ],
          "description": "دریاچه قیر در شهرستان قیر و کارزین واقع شده و به عنوان یکی از دریاچه‌های مهم و طبیعی استان فارس شناخته می‌شود. این دریاچه به دلیل موقعیت جغرافیایی خاص و تنوع زیستی، زیستگاه پرندگان مهاجر و گونه‌های مختلف جانوری است.",
          "vote": [
            {
              "labels": [
                "Acceptable"
              ]
            }
          ]
        },
        {
          "name": "دریاچه زرقان",
          "images": [],
          "description": "دریاچه زرقان در نزدیکی شیراز واقع شده و به عنوان یکی از دریاچه‌های زیبا و طبیعی استان فارس شناخته می‌شود. این دریاچه به دلیل تنوع زیستی و زیبایی‌های طبیعی، مقصدی مناسب برای گردشگران و طبیعت‌گردان است.",
          "vote": [
            {
              "labels": [
                "Acceptable"
              ]
            }
          ]
        },
        {
          "name": "دریاچه فامور",
          "images": [
            "https://upload.wikimedia.org/wikipedia/commons/5/51/Moshir_Bridge_on_Dalaki_river_Borazjan_Iran.jpg"
          ],
          "description": "دریاچه فامور در شهرستان کازرون واقع شده و به عنوان یکی از دریاچه‌های زیبا و طبیعی استان فارس شناخته می‌شود. این دریاچه به دلیل تنوع زیستی و زیبایی‌های طبیعی، مقصدی مناسب برای گردشگران و طبیعت‌گردان است.",
          "vote": [
            {
              "labels": [
                "Acceptable"
              ]
            }
          ]
        }
      ]
    },
    {
      "name": "رودخانه‌ها",
      "description": [
        {
          "name": "رودخانه کر",
          "images": [
            "https://upload.wikimedia.org/wikipedia/commons/0/0d/Paddies_around_Kor_River%2C_Kamfirouz_%D8%B4%D8%A7%D9%84%DB%8C%D8%B2%D8%A7%D8%B1%D9%87%D8%A7%DB%8C_%D8%A7%D8%B7%D8%B1%D8%A7%D9%81_%D8%B1%D9%88%D8%AF_%DA%A9%D8%B1%D8%8C_%DA%A9%D8%A7%D9%85%D9%81%DB%8C%D8%B1%D9%88%D8%B2_-_panoramio.jpg"
          ],
          "description": "رودخانه کر یکی از مهم‌ترین رودخانه‌های استان فارس است که از کوه‌های زاگرس سرچشمه می‌گیرد و به سمت جنوب جریان دارد. این رودخانه به عنوان منبع آب کشاورزی و شرب در منطقه اهمیت دارد و در طول مسیر خود، دشت‌ها و زمین‌های حاصلخیز را آبیاری می‌کند.",
          "vote": [
            {
              "labels": [
                "Acceptable"
              ]
            }
          ]
        },
        {
          "name": "رودخانه‌های فسا",
          "images": [
            "https://upload.wikimedia.org/wikipedia/commons/f/f4/Jahrom_Shour_River_%281%29.jpg"
          ],
          "description": "رودخانه‌های فسا از رشته‌کوه‌های زاگرس سرچشمه می‌گیرند و به سمت دشت‌های پایین‌دست جریان دارند. این رودخانه‌ها به عنوان منابع آب شیرین برای کشاورزی و شرب در منطقه اهمیت دارند و در طول مسیر خود، پوشش گیاهی متنوعی را ایجاد می‌کنند.",
          "vote": [
            {
              "labels": [
                "Acceptable"
              ]
            }
          ]
        },
        {
          "name": "رودخانه شاپور",
          "images": [
            "https://upload.wikimedia.org/wikipedia/commons/a/af/IranBishapur1.jpg"
          ],
          "description": "رودخانه شاپور در استان فارس واقع شده و به عنوان یکی از رودخانه‌های مهم منطقه شناخته می‌شود. این رودخانه به عنوان منبع آب شیرین برای کشاورزی و شرب در منطقه اهمیت دارد و در طول مسیر خود، پوشش گیاهی متنوعی را ایجاد می‌کند.",
          "vote": [
            {
              "labels": [
                "Acceptable"
              ]
            }
          ]
        },
        {
          "name": "رودخانه دالکی",
          "images": [
            "https://upload.wikimedia.org/wikipedia/commons/5/51/Moshir_Bridge_on_Dalaki_river_Borazjan_Iran.jpg"
          ],
          "description": "رودخانه دالکی از رشته‌کوه‌های زاگرس سرچشمه می‌گیرد و به سمت دشت‌های پایین‌دست جریان دارد. این رودخانه به عنوان منبع آب شیرین برای کشاورزی و شرب در منطقه اهمیت دارد و در طول مسیر خود، پوشش گیاهی متنوعی را ایجاد می‌کند.",
          "vote": [
            {
              "labels": [
                "Acceptable"
              ]
            }
          ]
        },
        {
          "name": "رودخانه‌های گراش",
          "images": [],
          "description": "رودخانه‌های گراش از رشته‌کوه‌های زاگرس سرچشمه می‌گیرند و به سمت دشت‌های پایین‌دست جریان دارند. این رودخانه‌ها به عنوان منابع آب شیرین برای کشاورزی و شرب در منطقه اهمیت دارند و در طول مسیر خود، پوشش گیاهی متنوعی را ایجاد می‌کنند.",
          "vote": [
            {
              "labels": [
                "Acceptable"
              ]
            }
          ]
        },
        {
          "name": "رودخانه‌های کازرون",
          "images": [
            "https://upload.wikimedia.org/wikipedia/commons/a/af/IranBishapur1.jpg"
          ],
          "description": "رودخانه‌های کازرون از رشته‌کوه‌های زاگرس سرچشمه می‌گیرند و به سمت دشت‌های پایین‌دست جریان دارند. این رودخانه‌ها به عنوان منابع آب شیرین برای کشاورزی و شرب در منطقه اهمیت دارند و در طول مسیر خود، پوشش گیاهی متنوعی را ایجاد می‌کنند.",
          "vote": [
            {
              "labels": [
                "Acceptable"
              ]
            }
          ]
        },
        {
          "name": "رودخانه‌های ارسنجان",
          "images": [],
          "description": "رودخانه‌های ارسنجان از رشته‌کوه‌های زاگرس سرچشمه می‌گیرند و به سمت دشت‌های پایین‌دست جریان دارند. این رودخانه‌ها به عنوان منابع آب شیرین برای کشاورزی و شرب در منطقه اهمیت دارند و در طول مسیر خود، پوشش گیاهی متنوعی را ایجاد می‌کنند.",
          "vote": [
            {
              "labels": [
                "Acceptable"
              ]
            }
          ]
        }
      ]
    },
    {
      "name": "کوه‌ها",
      "description": [
        {
          "name": "کوه‌های زاگرس",
          "images": [
            "https://upload.wikimedia.org/wikipedia/commons/f/f4/Ecoregion_PA0446.svg"
          ],
          "description": "کوه‌های زاگرس در استان فارس واقع شده و دارای ارتفاعات بالایی هستند. این کوه‌ها به عنوان یکی از مهم‌ترین رشته‌کوه‌های ایران شناخته می‌شوند و به دلیل تنوع زیستی و پوشش گیاهی غنی، زیستگاه بسیاری از گونه‌های جانوری و گیاهی هستند. این کوه‌ها به عنوان مرز طبیعی بین استان‌های فارس و کهگیلویه و بویراحمد عمل می‌کنند.",
          "vote": [
            {
              "labels": [
                "Acceptable"
              ]
            }
          ]
        },
        {
          "name": "کوه‌های سپیدان",
          "images": [
            "https://www.iranhotelonline.com/blog/wp-content/uploads/2023/05/1683196295_%D8%AF%D8%B1%DB%8C%D8%A7%DA%86%D9%87-%D9%88-%DA%A9%D9%88%D9%87-%D8%A8%D8%B1%D9%85-%D9%81%DB%8C%D8%B1%D9%88%D8%B2-%D8%B3%D9%BE%DB%8C%D8%AF%D8%A7%D9%86-%D8%B4%DB%8C%D8%B1%D8%A7%D8%B2-jpg.webp"
          ],
          "description": "کوه‌های سپیدان در شمال غربی شیراز قرار دارند و به دلیل ارتفاعات بلند و مناظر طبیعی زیبا، مقصدی محبوب برای کوهنوردان و طبیعت‌گردان هستند. این کوه‌ها پوشش گیاهی متنوعی دارند و به عنوان یکی از مناطق حفاظت‌شده استان فارس شناخته می‌شوند.",
          "vote": [
            {
              "labels": [
                "Acceptable"
              ]
            }
          ]
        },
        {
          "name": "کوه‌های داراب",
          "images": [
            "https://cdn.yjc.ir/files/fa/news/1400/10/19/15444592_551.jpg"
          ],
          "description": "کوه‌های داراب در استان فارس واقع شده و به دلیل تنوع زیستی و مناظر طبیعی زیبا، مقصدی محبوب برای گردشگران هستند. این کوه‌ها دارای پوشش گیاهی غنی و آبشارهای زیبا هستند که به جذابیت این منطقه افزوده است.",
          "vote": [
            {
              "labels": [
                "Acceptable"
              ]
            }
          ]
        },
        {
          "name": "کوه‌های ممسنی",
          "images": [],
          "description": "کوه‌های ممسنی در غرب استان فارس واقع شده و به دلیل ارتفاعات بلند و مناظر طبیعی زیبا، مقصدی محبوب برای کوهنوردان و طبیعت‌گردان هستند. این کوه‌ها دارای پوشش گیاهی متنوع و زیستگاه بسیاری از گونه‌های جانوری و گیاهی هستند.",
          "vote": [
            {
              "labels": [
                "Needs Revision"
              ]
            }
          ]
        },
        {
          "name": "کوه‌های تودج",
          "images": [],
          "description": "کوه‌های تودج در شهرستان فسا واقع شده و به عنوان یکی از مناطق کوهستانی با چشم‌اندازهای زیبا شناخته می‌شوند. این کوه‌ها دارای مسیرهای متنوع برای کوهنوردی و پیاده‌روی هستند و به دلیل آب و هوای معتدل، در فصل‌های مختلف سال مورد توجه گردشگران قرار می‌گیرند.",
          "vote": [
            {
              "labels": [
                "Needs Revision"
              ]
            }
          ]
        },
        {
          "name": "کوه‌های تنگ چوگان",
          "images": [
            "https://upload.wikimedia.org/wikipedia/commons/3/36/Bakhtegan_Lake.jpg"
          ],
          "description": "کوه‌های تنگ چوگان در نزدیکی شهر کازرون واقع شده و به دلیل مناظر طبیعی و تاریخی خود، توجه بسیاری از گردشگران را جلب می‌کنند. این کوه‌ها دارای دره‌های عمیق و پوشش گیاهی متنوع هستند که محیطی دلپذیر برای استراحت و تفریح در میان طبیعت فراهم می‌کند.",
          "vote": [
            {
              "labels": [
                "Acceptable"
              ]
            }
          ]
        },
        {
          "name": "کوه‌های زرقان",
          "images": [],
          "description": "کوه‌های زرقان در نزدیکی شیراز واقع شده و به عنوان یکی از مناطق طبیعی زیبا و جذاب استان فارس شناخته می‌شوند. این کوه‌ها دارای پوشش گیاهی متنوع و مناظر طبیعی زیبا هستند که به جذابیت این منطقه افزوده است.",
          "vote": [
            {
              "labels": [
                "Needs Revision"
              ]
            }
          ]
        },
        {
          "name": "کوه‌های هرمز",
          "images": [],
          "description": "کوه‌های هرمز در نزدیکی شیراز واقع شده و به عنوان یکی از مناطق طبیعی زیبا و جذاب استان فارس شناخته می‌شوند. این کوه‌ها دارای پوشش گیاهی متنوع و مناظر طبیعی زیبا هستند که به جذابیت این منطقه افزوده است.",
          "vote": [
            {
              "labels": [
                "Needs Revision"
              ]
            }
          ]
        },
        {
          "name": "کوه‌های مرودشت",
          "images": [],
          "description": "کوه‌های مرودشت از رشته‌کوه‌های زاگرس سرچشمه می‌گیرند و به سمت دشت‌های پایین‌دست جریان دارند. این کوه‌ها به دلیل پوشش گیاهی متنوع و مناظر طبیعی جذاب، مقصدی مناسب برای گردشگران و پژوهشگران هستند.",
          "vote": [
            {
              "labels": [
                "Needs Revision"
              ]
            }
          ]
        },
        {
          "name": "کوه‌های کازرون",
          "images": [],
          "description": "کوه‌های کازرون در استان فارس واقع شده و به دلیل تنوع زیستی و مناظر طبیعی زیبا، مقصدی محبوب برای کوهنوردان و طبیعت‌گردان هستند. این کوه‌ها دارای پوشش گیاهی غنی و آبشارهای زیبا هستند که به جذابیت این منطقه افزوده است.",
          "vote": [
            {
              "labels": [
                "Needs Revision"
              ]
            }
          ]
        },
        {
          "name": "کوه‌های قلات",
          "images": [],
          "description": "کوه‌های قلات در شمال شیراز واقع شده و به عنوان یکی از مناطق طبیعی زیبا و جذاب استان فارس شناخته می‌شوند. این کوه‌ها دارای پوشش گیاهی متنوع و مناظر طبیعی زیبا هستند که به جذابیت این منطقه افزوده است.",
          "vote": [
            {
              "labels": [
                "Needs Revision"
              ]
            }
          ]
        },
        {
          "name": "کوه‌های بیضاء",
          "images": [
            "https://shiraz-tourist.com/wp-content/uploads/2021/06/139401241243108995090984.jpg"
          ],
          "description": "کوه‌های بیضاء در نزدیکی شیراز واقع شده و به عنوان یکی از مناطق طبیعی زیبا و جذاب استان فارس شناخته می‌شوند. این کوه‌ها دارای پوشش گیاهی متنوع و مناظر طبیعی زیبا هستند که به جذابیت این منطقه افزوده است.",
          "vote": [
            {
              "labels": [
                "Acceptable"
              ]
            }
          ]
        },
        {
          "name": "کوه‌های بمو",
          "images": [
            "https://upload.wikimedia.org/wikipedia/commons/a/a4/Bamoo_mountain.jpg"
          ],
          "description": "کوه‌های بمو در نزدیکی شیراز واقع شده و به عنوان یکی از مناطق طبیعی زیبا و جذاب استان فارس شناخته می‌شوند. این کوه‌ها دارای پوشش گیاهی متنوع و مناظر طبیعی زیبا هستند که به جذابیت این منطقه افزوده است.",
          "vote": [
            {
              "labels": [
                "Acceptable"
              ]
            }
          ]
        }
      ]
    },
    {
      "name": "تنگه‌ها",
      "description": [
        {
          "name": "تنگه رغز",
          "images": [
            "https://upload.wikimedia.org/wikipedia/commons/thumb/3/39/Raghezdarab.jpg/1200px-Raghezdarab.jpg"
          ],
          "description": "تنگه رغز یکی از زیباترین تنگه‌های استان فارس است که به دلیل مناظر طبیعی و پوشش گیاهی متنوع، مقصدی مناسب برای طبیعت‌گردان و عکاسان محسوب می‌شود. این تنگه با درختان انبوه و آب‌های زلال، محیطی آرامش‌بخش و دلپذیر را فراهم می‌آورد.",
          "vote": [
            {
              "labels": [
                "Acceptable"
              ]
            }
          ]
        }
      ]
    },
    {
      "name": "باغ‌ها",
      "description": [
        {
          "name": "باغ ارم",
          "images": [
            "https://upload.wikimedia.org/wikipedia/commons/b/bb/Eram%2C_Shiraz%2C_Fars_Province%2C_Iran_-_panoramio_%282%29.jpg"
          ],
          "description": "باغ ارم یکی از باغ‌های تاریخی و مشهور شیراز است که به دلیل پوشش گیاهی متنوع و درختان کهن‌سال خود شناخته می‌شود. این باغ با مساحت تقریبی 11000 متر مربع و طراحی زیبا، شامل درختان نارنج، کاج و گل‌های رنگارنگ است. باغ ارم به عنوان یک اثر ملی ثبت شده و نمایانگر هنر باغ‌سازی ایرانی در دوره قاجار است.",
          "vote": [
            {
              "labels": [
                "Acceptable"
              ]
            }
          ]
        },
        {
          "name": "باغ نارنجستان قوام",
          "images": [
            "https://upload.wikimedia.org/wikipedia/commons/9/92/Qavam_House_%D8%A8%D8%A7%D8%BA_%D9%86%D8%A7%D8%B1%D9%86%D8%AC%D8%B3%D8%AA%D8%A7%D9%86_%D9%82%D9%88%D8%A7%D9%85_%D8%AF%D8%B1_%D8%B4%DB%8C%D8%B1%D8%A7%D8%B2_10.jpg"
          ],
          "description": "باغ نارنجستان قوام در شیراز، با پوشش گیاهی منحصر به فرد و درختان نارنج، به عنوان یکی از باغ‌های تاریخی ایران شناخته می‌شود. این باغ با طراحی ایرانی و معماری زیبا، فضایی آرامش‌بخش برای بازدیدکنندگان فراهم می‌کند و به عنوان یک اثر ملی در فهرست میراث فرهنگی ایران ثبت شده است.",
          "vote": [
            {
              "labels": [
                "Acceptable"
              ]
            }
          ]
        }
      ]
    },
    {
      "name": "دشت‌ها",
      "description": [
        {
          "name": "دشت ارژن",
          "images": [
            "https://upload.wikimedia.org/wikipedia/commons/a/a3/Arzhan_lake%2C_Fars_2.jpg"
          ],
          "description": "دشت ارژن با پوشش گیاهی متنوع شامل گیاهان بومی و درختان زینتی، محلی مناسب برای زندگی گونه‌های مختلف جانوری است. این دشت به عنوان یک منطقه حفاظت‌شده، اهمیت زیست‌محیطی بالایی دارد و به دلیل تنوع زیستی، مقصدی محبوب برای طبیعت‌گردان و پژوهشگران محسوب می‌شود.",
          "vote": [
            {
              "labels": [
                "Acceptable"
              ]
            }
          ]
        }
      ]
    },
    {
      "name": "منطقه‌های حفاظت شده",
      "description": [
        {
          "name": "منطقه حفاظت‌شده بمو",
          "images": [],
          "description": "منطقه حفاظت‌شده بمو، با پوشش گیاهی متنوع شامل جنگل‌های بلوط و گیاهان دارویی، یکی از مناطق مهم زیست‌محیطی استان فارس است. این منطقه به عنوان زیستگاه گونه‌های مختلف جانوری و گیاهی، اهمیت بالایی برای حفظ تنوع زیستی دارد و همچنین به عنوان مقصدی برای طبیعت‌گردی شناخته می‌شود.",
          "vote": [
            {
              "labels": [
                "Needs Revision"
              ]
            }
          ]
        }
      ]
    },
    {
      "name": "پوشش گیاهی",
      "description": [
        {
          "name": "درختان جنگلی",
          "images": [],
          "description": "پوشش گیاهی استان فارس را درختان جنگلی تشکیل می‌دهند؛ از مهم‌ترین گونه‌های درختی این استان می‌توان به بادام کوهی، بنه و بلوط اشاره کرد.",
          "vote": [
            {
              "labels": [
                "Needs Revision"
              ]
            }
          ]
        },
        {
          "name": "گیاهان دارویی و صنعتی",
          "images": [],
          "description": "از مهم‌ترین گونه‌های گیاهان دارویی و صنعتی استان فارس می‌توان شیرین بیان، گل گاوزبان، کتیرا، آنغوزه و گون را نام برد.",
          "vote": [
            {
              "labels": [
                "Needs Revision"
              ]
            }
          ]
        },
        {
          "name": "مناطق حفاظت شده",
          "images": [],
          "description": "مناطق حفاظت شده استان فارس محل رویش بسیاری از گونه‌های گیاهی بومی و کمیاب منطقه هستند.",
          "vote": [
            {
              "labels": [
                "Needs Revision"
              ]
            }
          ]
        },
        {
          "name": "پارک ملی بمو",
          "images": [],
          "description": "پارک ملی بمو (واقع در جنوب غرب شیراز) از نظر پوشش گیاهی بسیار غنی است و تاکنون بیش از ۲۸۰ گونه گیاهی در آن شناسایی و نمونه‌برداری شده است.",
          "vote": [
            {
              "labels": [
                "Needs Revision"
              ]
            }
          ]
        }
      ]
    }
  ],
  "topography": [
    {
      "name": "اقلیم منطقه",
      "description": [
        "ناحیه کوهستانی (آپاختر، آپاختر باختر و باختر): زمستان‌های خیلی سرد، تابستان‌های معتدل و پوشش گیاهی برجسته، با بارش سالانه ۴۰۰–۶۰۰ میلی‌متر",
        "ناحیه مرکزی: زمستان سرد همراه با بارندگی و تابستان گرم و خشک، با بارش سالانه ۲۰۰–۴۰۰ میلی‌متر (شامل شهرهای شیراز، جهرم، فسا، فیروزآباد و کازرون)",
        "ناحیه نیمروز و نیمروز خاوری: زمستان معتدل، تابستان بسیار گرم، با بارش سالانه ۱۰۰–۲۰۰ میلی‌متر، رطوبت نسبی ۱۲٫۵–۸۴٫۵٪ و ۳۴ روز یخبندان در سال (شامل شهرهای گراش، لار، لامرد، جویم، اوز و خنج)"
      ],
      "vote": [
        {
          "labels": [
            "Needs Revision"
          ]
        }
      ]
    },
    {
      "name": "توپوگرافی",
      "description": [
        {
          "name": "دشت ارژن",
          "description": "دشت ارژن در شمال شرقی شیراز واقع شده و با مساحتی حدود 500 کیلومتر مربع، یکی از دشت‌های وسیع و حاصلخیز استان فارس به شمار می‌آید. این دشت به دلیل وجود منابع آب زیرزمینی و خاک حاصلخیز، به عنوان یکی از مناطق کشاورزی مهم در فارس شناخته می‌شود. همچنین، دشت ارژن به دلیل موقعیت جغرافیایی خاص خود، زیستگاه گونه‌های مختلفی از پرندگان و جانوران است. از ویژگی‌های این دشت می‌توان به تنوع گیاهی، وجود چشمه‌ها و قنات‌های متعدد و همچنین چشم‌اندازهای طبیعی زیبا اشاره کرد.",
          "vote": [
            {
              "labels": [
                "Acceptable"
              ]
            }
          ]
        },
        {
          "name": "فلات شیراز",
          "description": "فلات شیراز یکی از بخش‌های مهم جغرافیایی استان فارس است که در ارتفاعی حدود 1500 متر از سطح دریا قرار دارد. این فلات به دلیل وجود تپه‌های کوچک و دره‌های عمیق، تنوع منظری خاصی دارد. همچنین، این فلات به عنوان یکی از مناطق با آب و هوای معتدل و مناسب برای کشاورزی و باغداری شناخته می‌شود. ویژگی‌های زمین‌شناسی این فلات شامل سنگ‌های رسوبی و آتشفشانی است که به غنای معدنی این منطقه افزوده است.",
          "vote": [
            {
              "labels": [
                "Acceptable"
              ]
            }
          ]
        },
        {
          "name": "کوه‌های زاگرس",
          "description": "کوه‌های زاگرس در غرب و شمال غرب استان فارس قرار دارند و به عنوان یکی از مهم‌ترین رشته‌کوه‌های ایران شناخته می‌شوند. این کوه‌ها به دلیل ارتفاعات بالا، آب و هوای متنوعی دارند و زیستگاه بسیاری از گونه‌های گیاهی و جانوری هستند. همچنین، وجود معادن غنی از سنگ‌های معدنی مانند گچ و سنگ آهک در این نواحی، اهمیت اقتصادی بالایی به این منطقه بخشیده است. کوه‌های زاگرس همچنین به دلیل زیبایی‌های طبیعی و چشم‌اندازهای جذاب، مقصدی محبوب برای گردشگران محسوب می‌شوند.",
          "vote": [
            {
              "labels": [
                "Acceptable"
              ]
            }
          ]
        },
        {
          "name": "کوه‌های سعادت‌شهر",
          "description": "کوه‌های سعادت‌شهر در شمال غربی شیراز قرار دارند و به عنوان یکی از نواحی کوهستانی با آب و هوای معتدل شناخته می‌شوند. این کوه‌ها به دلیل وجود درختان بلوط و گیاهان دارویی، از نظر زیست‌محیطی اهمیت بالایی دارند. همچنین، کوه‌های سعادت‌شهر به عنوان یک منطقه گردشگری با امکانات مناسب برای کوهنوردی و طبیعت‌گردی، مورد توجه قرار گرفته‌اند. ارتفاعات این کوه‌ها به دلیل وجود چشمه‌های آب شیرین، به عنوان منابع آب شرب نیز مورد استفاده قرار می‌گیرند.",
          "vote": [
            {
              "labels": [
                "Acceptable"
              ]
            }
          ]
        },
        {
          "name": "دشت فسا",
          "description": "دشت فسا در شمال شرقی استان فارس واقع شده و به عنوان یکی از دشت‌های حاصلخیز و کشاورزی شناخته می‌شود. این دشت به دلیل وجود قنات‌ها و منابع آب زیرزمینی، به عنوان منطقه‌ای مناسب برای کشاورزی و باغداری محسوب می‌شود. همچنین، وجود تنوع گیاهی و جانوری در این دشت، آن را به یک منطقه با ارزش زیست‌محیطی تبدیل کرده است. این دشت همچنین به دلیل موقعیت جغرافیایی خاص خود، دارای آب و هوای معتدل و مناسب برای زندگی است.",
          "vote": [
            {
              "labels": [
                "Acceptable"
              ]
            }
          ]
        },
        {
          "name": "کوه‌های داراب",
          "description": "کوه‌های داراب در جنوب شرق استان فارس واقع شده و به عنوان یکی از نواحی کوهستانی با زیبایی‌های طبیعی شناخته می‌شوند. این کوه‌ها به دلیل وجود پوشش گیاهی متنوع و چشمه‌های آب شیرین، از نظر زیست‌محیطی اهمیت بالایی دارند. همچنین، کوه‌های داراب به عنوان مقصدی محبوب برای کوهنوردی و طبیعت‌گردی، مورد توجه گردشگران قرار گرفته‌اند. ارتفاعات این کوه‌ها به دلیل وجود سنگ‌های معدنی، به عنوان منابع اقتصادی نیز مورد استفاده قرار می‌گیرند.",
          "vote": [
            {
              "labels": [
                "Acceptable"
              ]
            }
          ]
        },
        {
          "name": "دشت ممسنی",
          "description": "دشت ممسنی در شمال غربی استان فارس واقع شده و به عنوان یکی از دشت‌های وسیع و حاصلخیز شناخته می‌شود. این دشت به دلیل وجود منابع آب زیرزمینی و خاک‌های مناسب برای کشاورزی، به عنوان منطقه‌ای مهم برای تولید محصولات زراعی و باغی محسوب می‌شود. همچنین، تنوع زیستی و وجود گونه‌های مختلف جانوری در این دشت، آن را به یک منطقه حفاظت‌شده و ارزشمند تبدیل کرده است. دشت ممسنی همچنین به دلیل موقعیت جغرافیایی خاص خود، دارای آب و هوای معتدل و مناسب برای زندگی است.",
          "vote": [
            {
              "labels": [
                "Acceptable"
              ]
            }
          ]
        },
        {
          "name": "کوه‌های ارسنجان",
          "description": "کوه‌های ارسنجان در شمال استان فارس واقع شده و به عنوان یکی از نواحی کوهستانی با آب و هوای معتدل شناخته می‌شوند. این کوه‌ها به دلیل وجود درختان بلوط و گیاهان دارویی، از نظر زیست‌محیطی اهمیت بالایی دارند. همچنین، کوه‌های ارسنجان به عنوان یک منطقه گردشگری با امکانات مناسب برای کوهنوردی و طبیعت‌گردی، مورد توجه قرار گرفته‌اند. ارتفاعات این کوه‌ها به دلیل وجود چشمه‌های آب شیرین، به عنوان منابع آب شرب نیز مورد استفاده قرار می‌گیرند.",
          "vote": [
            {
              "labels": [
                "Acceptable"
              ]
            }
          ]
        },
        {
          "name": "دشت نی‌ریز",
          "description": "دشت نی‌ریز در شمال شرقی استان فارس واقع شده و به عنوان یکی از دشت‌های وسیع و حاصلخیز شناخته می‌شود. این دشت به دلیل وجود قنات‌ها و منابع آب زیرزمینی، به عنوان منطقه‌ای مناسب برای کشاورزی و باغداری محسوب می‌شود. همچنین، وجود تنوع گیاهی و جانوری در این دشت، آن را به یک منطقه با ارزش زیست‌محیطی تبدیل کرده است. دشت نی‌ریز همچنین به دلیل موقعیت جغرافیایی خاص خود، دارای آب و هوای معتدل و مناسب برای زندگی است.",
          "vote": [
            {
              "labels": [
                "Acceptable"
              ]
            }
          ]
        },
        {
          "name": "دشت ابرکوه",
          "description": "دشت ابرکوه در شمال غربی استان فارس واقع شده است و به خاطر ویژگی‌های زمین‌شناسی خاص خود و وجود خاک‌های حاصلخیز مشهور است. این دشت به عنوان یکی از مناطق زراعی مهم استان فارس شناخته می‌شود و کشاورزی در آن رونق دارد. همچنین، وجود قنات‌ها و منابع آب زیرزمینی در این منطقه به کشاورزان کمک می‌کند.",
          "vote": [
            {
              "labels": [
                "Acceptable"
              ]
            }
          ]
        },
        {
          "name": "دشت کربال",
          "description": "دشت کربال در شهرستان شیراز واقع شده و به خاطر تنوع زیستی و پوشش گیاهی غنی‌اش معروف است. این دشت دارای خاک‌های مناسب برای کشت انواع محصولات زراعی است و به عنوان یکی از مناطق مهم کشاورزی استان فارس به شمار می‌رود. همچنین، این منطقه به خاطر وجود آبشارها و چشمه‌ها، جاذبه‌های طبیعی زیادی دارد.",
          "vote": [
            {
              "labels": [
                "Acceptable"
              ]
            }
          ]
        },
        {
          "name": "دشت زرقان",
          "description": "دشت زرقان در شمال شرقی شیراز واقع شده و به عنوان یکی از دشت‌های مهم استان فارس شناخته می‌شود. این دشت به خاطر آب و هوای مناسب و خاک‌های حاصلخیز، به عنوان منطقه‌ای برای کشت محصولات زراعی و باغی مورد استفاده قرار می‌گیرد. همچنین، وجود قنات‌ها در این منطقه به تأمین آب کشاورزی کمک می‌کند.",
          "vote": [
            {
              "labels": [
                "Acceptable"
              ]
            }
          ]
        },
        {
          "name": "دشت رستم",
          "description": "دشت رستم در غرب استان فارس واقع شده و به خاطر مناظر طبیعی و کوه‌های اطرافش مشهور است. این دشت به عنوان منطقه‌ای با پتانسیل بالا برای کشاورزی و دامداری شناخته می‌شود و همچنین دارای منابع آب زیرزمینی قابل توجهی است که به کشاورزان محلی کمک می‌کند.",
          "vote": [
            {
              "labels": [
                "Acceptable"
              ]
            }
          ]
        },
        {
          "name": "دشت شاپور",
          "description": "دشت شاپور در شهرستان کازرون واقع شده و به خاطر وجود آثار باستانی و تاریخی در اطرافش شناخته می‌شود. این دشت دارای خاک‌های حاصلخیز و منابع آبی مناسب است که امکان کشت محصولات زراعی را فراهم می‌آورد. همچنین، وجود رودخانه شاپور در این منطقه یکی از ویژگی‌های طبیعی مهم آن به شمار می‌رود.",
          "vote": [
            {
              "labels": [
                "Acceptable"
              ]
            }
          ]
        },
        {
          "name": "دشت مرودشت",
          "description": "دشت مرودشت به عنوان یکی از دشت‌های وسیع و حاصلخیز استان فارس شناخته می‌شود. این دشت در نزدیکی آثار باستانی تخت جمشید واقع شده و به خاطر تاریخ غنی و کشاورزی موفق خود معروف است. خاک‌های این دشت به دلیل رسوبات رودخانه‌ای بسیار حاصلخیز هستند.",
          "vote": [
            {
              "labels": [
                "Acceptable"
              ]
            }
          ]
        },
        {
          "name": "دشت ارسنجان",
          "description": "دشت ارسنجان در شمال شهرستان ارسنجان واقع شده و به خاطر ویژگی‌های طبیعی و کشاورزی‌اش شناخته می‌شود. این دشت دارای آب و هوای معتدل و خاک‌های حاصلخیز است که امکان کشت محصولات کشاورزی را فراهم می‌آورد. همچنین، وجود چشمه‌ها و منابع آب زیرزمینی در این منطقه به تأمین آب کشاورزی کمک می‌کند.",
          "vote": [
            {
              "labels": [
                "Acceptable"
              ]
            }
          ]
        },
        {
          "name": "فلات نرگس",
          "description": "فلات نرگس در شهرستان شیراز واقع شده و به خاطر تنوع زیستی و پوشش گیاهی غنی‌اش مشهور است. این فلات به عنوان منطقه‌ای با آب و هوای مناسب برای کشت گیاهان دارویی و زراعی شناخته می‌شود. همچنین، وجود دشت‌های وسیع در اطراف آن به تأمین نیازهای کشاورزی کمک می‌کند.",
          "vote": [
            {
              "labels": [
                "Acceptable"
              ]
            }
          ]
        },
        {
          "name": "کوه‌های کازرون",
          "description": "کوه‌های کازرون در شهرستان کازرون واقع شده و به خاطر زیبایی‌های طبیعی و تنوع زیستی خود شناخته می‌شوند. این کوه‌ها به عنوان منطقه‌ای برای گردشگری و تفریح مورد استفاده قرار می‌گیرند و همچنین دارای منابع آبی و خاک‌های مناسب برای کشاورزی هستند.",
          "vote": [
            {
              "labels": [
                "Acceptable"
              ]
            }
          ]
        },
        {
          "name": "دشت بارز",
          "description": "دشت بارز در شمال غربی استان فارس واقع شده و به خاطر خاک‌های حاصلخیز و آب و هوای مناسبش شهرت دارد. این دشت به عنوان یکی از مناطق مهم کشاورزی استان فارس شناخته می‌شود و محصولات متنوعی از جمله غلات و میوه‌ها در آن کشت می‌شود.",
          "vote": [
            {
              "labels": [
                "Acceptable"
              ]
            }
          ]
        },
        {
          "name": "دشت قیر",
          "description": "دشت قیر در شهرستان قیر و کارزین واقع شده و به خاطر خاک‌های حاصلخیز و آب و هوای مناسبش شهرت دارد. این دشت به عنوان منطقه‌ای مهم برای کشاورزی و دامداری مورد استفاده قرار می‌گیرد و محصولات متنوعی از جمله غلات و سبزیجات در آن کشت می‌شود.",
          "vote": [
            {
              "labels": [
                "Acceptable"
              ]
            }
          ]
        },
        {
          "name": "دشت اقلید",
          "description": "دشت اقلید در شهرستان اقلید واقع شده و به خاطر ویژگی‌های طبیعی و کشاورزی‌اش شناخته می‌شود. این دشت دارای آب و هوای مناسب و خاک‌های حاصلخیز است که امکان کشت محصولات زراعی و باغی را فراهم می‌آورد.",
          "vote": [
            {
              "labels": [
                "Acceptable"
              ]
            }
          ]
        },
        {
          "name": "دشت بوانات",
          "description": "دشت بوانات در شهرستان بوانات واقع شده و به خاطر تنوع زیستی و منابع آبی خود شناخته می‌شود. این دشت به عنوان منطقه‌ای مهم برای کشاورزی و دامداری مورد استفاده قرار می‌گیرد و خاک‌های حاصلخیز آن امکان کشت محصولات متنوع را فراهم می‌آورد.",
          "vote": [
            {
              "labels": [
                "Acceptable"
              ]
            }
          ]
        },
        {
          "name": "دشت سپیدان",
          "description": "دشت سپیدان در شهرستان سپیدان واقع شده و به خاطر مناظر طبیعی و زیبایی‌های خیره‌کننده خود مشهور است. این دشت دارای منابع آبی و خاک‌های مناسب برای کشاورزی بوده و به عنوان منطقه‌ای برای گردشگری و تفریح مورد استفاده قرار می‌گیرد.",
          "vote": [
            {
              "labels": [
                "Acceptable"
              ]
            }
          ]
        },
        {
          "name": "دشت نورآباد",
          "description": "دشت نورآباد در شهرستان ممسنی واقع شده و به خاطر تنوع زیستی و منابع آبی خود شناخته می‌شود. این دشت به عنوان منطقه‌ای مهم برای کشاورزی و دامداری مورد استفاده قرار می‌گیرد و خاک‌های حاصلخیز آن امکان کشت محصولات متنوع را فراهم می‌آورد.",
          "vote": [
            {
              "labels": [
                "Acceptable"
              ]
            }
          ]
        },
        {
          "name": "دشت خفر",
          "description": "دشت خفر در شهرستان خفر واقع شده و به خاطر ویژگی‌های طبیعی و کشاورزی‌اش شناخته می‌شود. این دشت دارای آب و هوای مناسب و خاک‌های حاصلخیز است که امکان کشت محصولات زراعی و باغی را فراهم می‌آورد.",
          "vote": [
            {
              "labels": [
                "Acceptable"
              ]
            }
          ]
        },
        {
          "name": "دشت جهرم",
          "description": "دشت جهرم در شهرستان جهرم واقع شده و به خاطر خاک‌های حاصلخیز و آب و هوای مناسبش شهرت دارد. این دشت به عنوان یکی از مناطق مهم کشاورزی استان فارس شناخته می‌شود و محصولات متنوعی از جمله غلات و میوه‌ها در آن کشت می‌شود.",
          "vote": [
            {
              "labels": [
                "Acceptable"
              ]
            }
          ]
        },
        {
          "name": "دشت شیراز",
          "description": "دشت شیراز در مرکز استان فارس واقع شده و به خاطر ویژگی‌های طبیعی و تاریخی‌اش شناخته می‌شود. این دشت به عنوان منطقه‌ای مهم برای کشاورزی و دامداری مورد استفاده قرار می‌گیرد و همچنین به خاطر وجود آثار باستانی و فرهنگی در اطرافش، جاذبه‌های گردشگری زیادی دارد.",
          "vote": [
            {
              "labels": [
                "Acceptable"
              ]
            }
          ]
        },
        {
          "name": "دشت داراب",
          "description": "دشت داراب در شهرستان داراب واقع شده و به خاطر ویژگی‌های طبیعی و کشاورزی‌اش شناخته می‌شود. این دشت دارای آب و هوای مناسب و خاک‌های حاصلخیز است که امکان کشت محصولات زراعی و باغی را فراهم می‌آورد.",
          "vote": [
            {
              "labels": [
                "Acceptable"
              ]
            }
          ]
        },
        {
          "name": "دشت اباده",
          "description": "دشتاباده یکی از دشت‌های واقع در استان فارس است که در شهرستان شیراز قرار دارد. این دشت به دلیل موقعیت جغرافیایی خاص خود، دارای آب و هوای معتدل و شرایط مناسب کشاورزی است. مساحت این دشت به حدود 150 کیلومتر مربع می‌رسد و عمدتاً به کشت محصولات زراعی و باغی اختصاص یافته است.",
          "vote": [
            {
              "labels": [
                "Acceptable"
              ]
            }
          ]
        },
        {
          "name": "دشت سروستان",
          "description": "دشتسروستان در شهرستان سروستان واقع شده و به عنوان یکی از دشت‌های حاصلخیز فارس شناخته می‌شود. این دشت به دلیل وجود آب‌های زیرزمینی و قنات‌ها، برای کشاورزی مناسب است و به کشت محصولات متنوعی مانند گندم و جو می‌پردازد.",
          "vote": [
            {
              "labels": [
                "Acceptable"
              ]
            }
          ]
        },
        {
          "name": "دشت فراشبند",
          "description": "دشتفراشبند در شهرستان فراشبند واقع شده و به عنوان یک منطقه کشاورزی با آب و هوای گرم و خشک شناخته می‌شود. این دشت به دلیل وجود چشمه‌ها و قنات‌ها، به کشت محصولات زراعی و باغی کمک می‌کند و از نظر اقتصادی برای ساکنان منطقه مهم است.",
          "vote": [
            {
              "labels": [
                "Acceptable"
              ]
            }
          ]
        },
        {
          "name": "دشت ریگان",
          "description": "دشتریگان در شهرستان رستم واقع شده و به عنوان یک دشت وسیع و حاصلخیز شناخته می‌شود. این دشت به دلیل وجود منابع آبی و خاک‌های مناسب، به کشاورزی و دامداری اختصاص یافته و از نظر اقتصادی اهمیت دارد.",
          "vote": [
            {
              "labels": [
                "Acceptable"
              ]
            }
          ]
        },
        {
          "name": "دشت سعادت شهر",
          "description": "دشتسعادتشهر در شهرستان سعادتشهر واقع شده و به عنوان یکی از دشت‌های مهم فارس شناخته می‌شود. این دشت به دلیل وجود منابع آبی و خاک‌های حاصلخیز، به کشاورزی و دامداری اختصاص یافته و از نظر اقتصادی اهمیت دارد.",
          "vote": [
            {
              "labels": [
                "Acceptable"
              ]
            }
          ]
        },
        {
          "name": "دشت بید",
          "description": "دشتبید در شهرستان بید واقع شده و به عنوان یک دشت وسیع و حاصلخیز شناخته می‌شود. این دشت به دلیل وجود منابع آبی و خاک‌های مناسب، به کشاورزی و دامداری اختصاص یافته و از نظر اقتصادی اهمیت دارد.",
          "vote": [
            {
              "labels": [
                "Acceptable"
              ]
            }
          ]
        },
        {
          "name": "دشت پارس‌آباد",
          "description": "دشتپارس‌آباد در شهرستان پارس‌آباد واقع شده و به عنوان یک دشت وسیع و حاصلخیز شناخته می‌شود. این دشت به دلیل وجود منابع آبی و خاک‌های مناسب، به کشاورزی و دامداری اختصاص یافته و از نظر اقتصادی اهمیت دارد.",
          "vote": [
            {
              "labels": [
                "Unacceptable"
              ]
            }
          ]
        },
        {
          "name": "دشت قائمیه",
          "description": "دشتقائمیه در شهرستان قایمیه واقع شده و به عنوان یکی از دشت‌های مهم فارس شناخته می‌شود. این دشت به دلیل وجود منابع آبی و خاک‌های حاصلخیز، به کشاورزی و دامداری اختصاص یافته و از نظر اقتصادی اهمیت دارد.",
          "vote": [
            {
              "labels": [
                "Acceptable"
              ]
            }
          ]
        },
        {
          "name": "دشت کازرون",
          "description": "دشتکازرون یکی از دشت‌های مهم استان فارس است که در شهرستان کازرون واقع شده است. این دشت با مساحتی بالغ بر 300 کیلومتر مربع، به خاطر خاک حاصلخیز و منابع آبی مناسب، به عنوان یکی از مناطق کشاورزی مهم شناخته می‌شود. دشتکازرون در نزدیکی کوه‌های زاگرس قرار دارد و آب و هوای آن تحت تأثیر این کوه‌ها است.",
          "vote": [
            {
              "labels": [
                "Acceptable"
              ]
            }
          ]
        },
        {
          "name": "دشت پاسارگاد",
          "description": "دشتپاسارگاد در نزدیکی شهر تاریخی پاسارگاد واقع شده است و به عنوان محل قرارگیری مقبره کوروش بزرگ شناخته می‌شود. این دشت به دلیل وجود آثار باستانی و تاریخی، اهمیت فرهنگی و تاریخی زیادی دارد. همچنین، اقلیم آن تحت تأثیر دشت‌های اطراف و کوه‌های زاگرس قرار دارد.",
          "vote": [
            {
              "labels": [
                "Acceptable"
              ]
            }
          ]
        }
      ]
    }
  ],
  "natural_resources": [
    {
      "name": "معادن معدنی",
      "description": [
        {
          "name": "سنگ آهک",
          "description": "سنگ آهک یکی از منابع معدنی مهم استان فارس است که در صنایع ساختمانی و تولید سیمان کاربرد دارد. این سنگ به دلیل مقاومت بالا و سهولت در استخراج، در پروژه‌های عمرانی به کار می‌رود. معادن سنگ آهک در نقاط مختلف استان، به ویژه در شهرستان‌های فارس و مرودشت قرار دارند.",
          "vote": [
            {
              "labels": [
                "Acceptable"
              ]
            }
          ]
        },
        {
          "name": "مارن",
          "description": "مارن یک نوع سنگ رسوبی است که در استان فارس به وفور یافت می‌شود. این ماده معدنی به خصوص در تولید آجر و سفال کاربرد دارد و به دلیل ویژگی‌های فیزیکی مناسب، در صنعت ساختمان‌سازی نیز مورد استفاده قرار می‌گیرد.",
          "vote": [
            {
              "labels": [
                "Acceptable"
              ]
            }
          ]
        },
        {
          "name": "سنگ گچ",
          "description": "سنگ گچ یکی دیگر از منابع معدنی استان فارس است که در تولید گچ ساختمانی و صنایع شیمیایی کاربرد دارد. معادن سنگ گچ در شهرستان‌های کازرون و شیراز واقع شده‌اند و به دلیل خواص عایق حرارتی و صوتی، در ساخت و ساز بسیار مورد توجه هستند.",
          "vote": [
            {
              "labels": [
                "Acceptable"
              ]
            }
          ]
        },
        {
          "name": "مرمریت",
          "description": "مرمریت یک سنگ تزئینی است که در استان فارس استخراج می‌شود و به دلیل زیبایی و دوام بالا، در نماهای داخلی و خارجی ساختمان‌ها مورد استفاده قرار می‌گیرد. این سنگ به خصوص در شهرستان‌های شیراز و سپیدان استخراج می‌شود.",
          "vote": [
            {
              "labels": [
                "Acceptable"
              ]
            }
          ]
        },
        {
          "name": "سنگ چینی",
          "description": "سنگ چینی از دیگر منابع معدنی استان فارس است که در صنایع ساختمانی و تزئینی کاربرد دارد. این سنگ به دلیل رنگ و طرح‌های متنوعی که دارد، در ساخت مجسمه‌ها و دکوراسیون داخلی استفاده می‌شود.",
          "vote": [
            {
              "labels": [
                "Acceptable"
              ]
            }
          ]
        },
        {
          "name": "خاک نسوز",
          "description": "خاک نسوز یکی از مواد معدنی با ارزش در استان فارس است که در صنایع سرامیک و شیشه‌سازی کاربرد دارد. این ماده به دلیل مقاومت بالا در برابر حرارت، در تولید محصولات با کیفیت بالا بسیار مورد توجه است.",
          "vote": [
            {
              "labels": [
                "Acceptable"
              ]
            }
          ]
        },
        {
          "name": "خاک صنعتی",
          "description": "خاک صنعتی در استان فارس به عنوان یکی از منابع معدنی مهم شناخته می‌شود و در تولید مصالح ساختمانی و صنایع شیمیایی به کار می‌رود. این ماده معدنی در شهرستان‌های مختلف استان استخراج می‌شود.",
          "vote": [
            {
              "labels": [
                "Acceptable"
              ]
            }
          ]
        },
        {
          "name": "نمک آبی",
          "description": "نمک آبی یکی از منابع معدنی استان فارس است که در صنایع غذایی و شیمیایی کاربرد دارد. این ماده به ویژه در شهرستان‌های نزدیک به دریاچه‌ها و آب‌های شور استخراج می‌شود.",
          "vote": [
            {
              "labels": [
                "Acceptable"
              ]
            }
          ]
        },
        {
          "name": "نمک سنگی",
          "description": "نمک سنگی از دیگر منابع معدنی استان فارس است که در صنایع غذایی و دارویی استفاده می‌شود. این نمک به دلیل خواص درمانی و طعم‌دهی، در بازارهای داخلی و خارجی مورد توجه قرار دارد.",
          "vote": [
            {
              "labels": [
                "Acceptable"
              ]
            }
          ]
        },
        {
          "name": "سیلیس",
          "description": "سیلیس یکی از مواد معدنی مهم در استان فارس است که در صنایع شیشه‌سازی و سرامیک کاربرد دارد. این ماده به دلیل ویژگی‌های فیزیکی و شیمیایی مناسب، در تولید محصولات با کیفیت بالا استفاده می‌شود.",
          "vote": [
            {
              "labels": [
                "Acceptable"
              ]
            }
          ]
        },
        {
          "name": "کوارتزیت",
          "description": "کوارتزیت یک سنگ دگرگونی است که در استان فارس استخراج می‌شود و به دلیل استحکام و زیبایی، در ساخت و ساز و دکوراسیون داخلی کاربرد دارد. این سنگ در شهرستان‌های مختلف استان یافت می‌شود.",
          "vote": [
            {
              "labels": [
                "Acceptable"
              ]
            }
          ]
        },
        {
          "name": "منگنز",
          "description": "منگنز یکی از عناصر معدنی با ارزش در استان فارس است که در صنایع فولادسازی و شیمیایی کاربرد دارد. این ماده به دلیل خواص آلیاژی، در تولید فولادهای با کیفیت بسیار مورد استفاده قرار می‌گیرد.",
          "vote": [
            {
              "labels": [
                "Acceptable"
              ]
            }
          ]
        },
        {
          "name": "سرب",
          "description": "سرب از دیگر منابع معدنی استان فارس است که در صنایع الکتریکی و باتری‌سازی کاربرد دارد. این ماده به دلیل خواص شیمیایی خاص، در تولید باتری‌های قابل شارژ و دیگر محصولات صنعتی استفاده می‌شود.",
          "vote": [
            {
              "labels": [
                "Acceptable"
              ]
            }
          ]
        },
        {
          "name": "روی",
          "description": "روی یکی از عناصر مهم معدنی در استان فارس است که در صنایع شیمیایی و دارویی کاربرد دارد. این ماده به دلیل خواص ضد زنگ، در تولید آلیاژها و پوشش‌های محافظتی استفاده می‌شود.",
          "vote": [
            {
              "labels": [
                "Acceptable"
              ]
            }
          ]
        },
        {
          "name": "کرومیت",
          "description": "کرومیت یکی از منابع معدنی با ارزش در استان فارس است که در صنایع فولاد و رنگ‌سازی کاربرد دارد. این ماده به دلیل خواص آلیاژی و رنگ‌دهی، در تولید محصولات با کیفیت بسیار مورد توجه است.",
          "vote": [
            {
              "labels": [
                "Acceptable"
              ]
            }
          ]
        },
        {
          "name": "باریت",
          "description": "باریت از دیگر منابع معدنی استان فارس است که در صنایع شیمیایی و حفاری نفت کاربرد دارد. این ماده به دلیل وزن مخصوص بالا، در تولید گل حفاری و دیگر محصولات صنعتی استفاده می‌شود.",
          "vote": [
            {
              "labels": [
                "Acceptable"
              ]
            }
          ]
        },
        {
          "name": "سنگ آهن",
          "description": "سنگ آهن یکی از منابع معدنی مهم در استان فارس است که در صنایع فولادسازی کاربرد دارد. این ماده به دلیل غنی بودن از آهن، در تولید فولاد و آلیاژهای آهنی بسیار مورد استفاده قرار می‌گیرد.",
          "vote": [
            {
              "labels": [
                "Acceptable"
              ]
            }
          ]
        },
        {
          "name": "مس",
          "description": "مس از دیگر منابع معدنی استان فارس است که در صنایع الکتریکی و ساختمانی کاربرد دارد. این ماده به دلیل خواص هدایت الکتریکی و حرارتی بالا، در تولید سیم و کابل‌های الکتریکی استفاده می‌شود.",
          "vote": [
            {
              "labels": [
                "Acceptable"
              ]
            }
          ]
        },
        {
          "name": "گرانیت",
          "description": "گرانیت یکی از سنگ‌های تزئینی با ارزش در استان فارس است که در ساختمان‌سازی و دکوراسیون داخلی کاربرد دارد. این سنگ به دلیل مقاومت و زیبایی، در نمای ساختمان‌ها بسیار مورد توجه قرار دارد.",
          "vote": [
            {
              "labels": [
                "Acceptable"
              ]
            }
          ]
        },
        {
          "name": "نیکل",
          "description": "نیکل یکی از عناصر معدنی با ارزش در استان فارس است که در صنایع فولاد و آلیاژسازی کاربرد دارد. این ماده به دلیل خواص ضد زنگ و مقاومت در برابر خوردگی، در تولید آلیاژهای خاص بسیار مورد استفاده قرار می‌گیرد.",
          "vote": [
            {
              "labels": [
                "Acceptable"
              ]
            }
          ]
        },
        {
          "name": "سنگ تراورتن",
          "description": "سنگ تراورتن یکی از سنگ‌های تزئینی است که در استان فارس استخراج می‌شود و به دلیل زیبایی و خواص عایق حرارتی، در نمای ساختمان‌ها و دکوراسیون داخلی کاربرد دارد. این سنگ به ویژه در شهرستان‌های محلات و کاشان یافت می‌شود.",
          "vote": [
            {
              "labels": [
                "Acceptable"
              ]
            }
          ]
        },
        {
          "name": "آهک",
          "description": "سنگ آهک یکی از منابع معدنی مهم در استان فارس است که به‌عنوان ماده اولیه در صنایع ساختمانی و تولید سیمان استفاده می‌شود. این سنگ در مناطق مختلف استان به‌ویژه در شهرستان‌های شیراز و مرودشت استخراج می‌شود.",
          "vote": [
            {
              "labels": [
                "Acceptable"
              ]
            }
          ]
        },
        {
          "name": "گچ",
          "description": "گچ یکی از مصالح ساختمانی است که در استان فارس استخراج می‌شود. این ماده معدنی در صنایع ساختمانی و دکوراسیون داخلی کاربرد دارد و معادن آن در مناطق مختلف استان قرار دارد.",
          "vote": [
            {
              "labels": [
                "Acceptable"
              ]
            }
          ]
        },
        {
          "name": "آزبست",
          "description": "آزبست ماده‌ای معدنی است که در صنایع ساختمانی و عایق‌کاری کاربرد دارد. در استان فارس، معادن آزبست وجود دارد که به‌عنوان منبعی مهم شناخته می‌شود.",
          "vote": [
            {
              "labels": [
                "Acceptable"
              ]
            }
          ]
        },
        {
          "name": "فلدسپات",
          "description": "فلدسپات یکی از مواد معدنی است که در صنایع سرامیک و شیشه‌سازی کاربرد دارد. در استان فارس، معادن فلدسپات وجود دارد که به‌عنوان منبعی کلیدی شناخته می‌شود.",
          "vote": [
            {
              "labels": [
                "Acceptable"
              ]
            }
          ]
        },
        {
          "name": "پتاس",
          "description": "پتاس یکی از مواد معدنی مهم در صنعت کشاورزی و کودسازی است. در استان فارس، معادن پتاس وجود دارد که به‌عنوان منبعی کلیدی شناخته می‌شود.",
          "vote": [
            {
              "labels": [
                "Acceptable"
              ]
            }
          ]
        },
        {
          "name": "گرافیت",
          "description": "گرافیت ماده‌ای معدنی است که در صنایع الکترونیک و باتری‌سازی کاربرد دارد. در استان فارس، معادن گرافیت وجود دارد که به‌عنوان منبعی مهم شناخته می‌شود.",
          "vote": [
            {
              "labels": [
                "Acceptable"
              ]
            }
          ]
        },
        {
          "name": "کائولن",
          "description": "کائولن نوعی خاک رس است که در صنایع سرامیک و کاغذسازی کاربرد دارد. در استان فارس، معادن کائولن وجود دارد که به‌عنوان منبعی کلیدی شناخته می‌شود.",
          "vote": [
            {
              "labels": [
                "Acceptable"
              ]
            }
          ]
        },
        {
          "name": "سولفور",
          "description": "سولفور ماده‌ای شیمیایی است که در صنایع شیمیایی و کشاورزی کاربرد دارد. در استان فارس، معادن سولفور وجود دارد که به‌عنوان منبعی مهم شناخته می‌شود.",
          "vote": [
            {
              "labels": [
                "Acceptable"
              ]
            }
          ]
        },
        {
          "name": "سیلیکون",
          "description": "سیلیکون ماده‌ای معدنی است که در صنایع الکترونیک و شیشه‌سازی کاربرد دارد. در استان فارس، معادن سیلیکون وجود دارد که به‌عنوان منبعی کلیدی شناخته می‌شود.",
          "vote": [
            {
              "labels": [
                "Acceptable"
              ]
            }
          ]
        },
        {
          "name": "کلسیت",
          "description": "کلسیت نوعی سنگ کربناته است که در صنایع ساختمانی و شیمیایی کاربرد دارد. در استان فارس، معادن کلسیت وجود دارد که به‌عنوان منبعی مهم شناخته می‌شود.",
          "vote": [
            {
              "labels": [
                "Acceptable"
              ]
            }
          ]
        },
        {
          "name": "مگنتیت",
          "description": "مگنتیت یکی از سنگ‌های آهن‌دار است که در صنایع فولادسازی کاربرد دارد. در استان فارس، معادن مگنتیت وجود دارد که به‌عنوان منبعی کلیدی شناخته می‌شود.",
          "vote": [
            {
              "labels": [
                "Acceptable"
              ]
            }
          ]
        },
        {
          "name": "آنتیموان",
          "description": "آنتیموان ماده‌ای معدنی است که در صنایع الکترونیک و شیمیایی کاربرد دارد. در استان فارس، معادن آنتیموان وجود دارد که به‌عنوان منبعی مهم شناخته می‌شود.",
          "vote": [
            {
              "labels": [
                "Acceptable"
              ]
            }
          ]
        },
        {
          "name": "تیتانیوم",
          "description": "تیتانیوم ماده‌ای معدنی است که در صنایع هوافضا و الکترونیک کاربرد دارد. در استان فارس، معادن تیتانیوم وجود دارد که به‌عنوان منبعی کلیدی شناخته می‌شود.",
          "vote": [
            {
              "labels": [
                "Acceptable"
              ]
            }
          ]
        },
        {
          "name": "زئولیت",
          "description": "زئولیت نوعی ماده معدنی است که در صنایع شیمیایی و کشاورزی کاربرد دارد. در استان فارس، معادن زئولیت وجود دارد که به‌عنوان منبعی مهم شناخته می‌شود.",
          "vote": [
            {
              "labels": [
                "Acceptable"
              ]
            }
          ]
        },
        {
          "name": "کبالت",
          "description": "کبالت ماده‌ای معدنی است که در صنایع الکترونیک و باتری‌سازی کاربرد دارد. در استان فارس، معادن کبالت وجود دارد که به‌عنوان منبعی کلیدی شناخته می‌شود.",
          "vote": [
            {
              "labels": [
                "Acceptable"
              ]
            }
          ]
        },
        {
          "name": "سولفید",
          "description": "سولفید ماده‌ای شیمیایی است که در صنایع شیمیایی و معدنی کاربرد دارد. در استان فارس، معادن سولفید وجود دارد که به‌عنوان منبعی مهم شناخته می‌شود.",
          "vote": [
            {
              "labels": [
                "Acceptable"
              ]
            }
          ]
        },
        {
          "name": "فلزات قیمتی",
          "description": "فلزات قیمتی مانند طلا و نقره در استان فارس به‌صورت پراکنده یافت می‌شوند. این فلزات در صنایع جواهرسازی و الکترونیک کاربرد دارند.",
          "vote": [
            {
              "labels": [
                "Acceptable"
              ]
            }
          ]
        },
        {
          "name": "زیولیت",
          "description": "زیولیت یک ماده معدنی با خاصیت جذب بالا است که در استان فارس استخراج می‌شود. این ماده در صنایع کشاورزی و محیط زیست کاربرد دارد. وجود منابع زیولیت در فارس می‌تواند به بهبود کیفیت خاک و آب در این منطقه کمک کند.",
          "vote": [
            {
              "labels": [
                "Acceptable"
              ]
            }
          ]
        }
      ]
    },
    {
      "name": "منابع آبی",
      "description": [
        {
          "name": "دریاچه مهارلو",
          "description": "دریاچه مهارلو یکی از دریاچه‌های بزرگ و شور استان فارس است که در 30 کیلومتری شرق شیراز واقع شده است. این دریاچه به عنوان یک اکوسیستم مهم، زیستگاه بسیاری از پرندگان مهاجر و محلی محسوب می‌شود. سطح آب دریاچه به دلیل تبخیر بالا در تابستان کاهش می‌یابد. همچنین، این دریاچه به دلیل غلظت بالای نمک، برای فعالیت‌های اقتصادی مانند استخراج نمک نیز مورد توجه است.",
          "vote": [
            {
              "labels": [
                "Acceptable"
              ]
            }
          ]
        },
        {
          "name": "رودخانه کر",
          "description": "رودخانه کر یکی از مهم‌ترین رودخانه‌های استان فارس است که از کوه‌های زاگرس سرچشمه می‌گیرد و به سمت جنوب جریان دارد. این رودخانه در طول مسیر خود به تأمین آب کشاورزی و شرب مناطق مختلف کمک می‌کند. همچنین، کر به عنوان یک منبع آبی مهم برای تأمین آب شرب شیراز و دیگر شهرهای اطراف شناخته می‌شود.",
          "vote": [
            {
              "labels": [
                "Acceptable"
              ]
            }
          ]
        },
        {
          "name": "قنات‌های شیراز",
          "description": "قنات‌های شیراز، سیستم‌های آبی زیرزمینی هستند که به‌منظور تأمین آب کشاورزی و شرب از اعماق زمین به سطح زمین می‌آیند. این قنات‌ها به دلیل مهارت‌های مهندسی و معماری خاص خود، به عنوان میراث فرهنگی و طبیعی استان فارس به شمار می‌روند. قنات‌ها در شیراز به تأمین آب برای باغ‌ها و مزارع کمک می‌کنند و نقش مهمی در زندگی روزمره مردم دارند.",
          "vote": [
            {
              "labels": [
                "Acceptable"
              ]
            }
          ]
        },
        {
          "name": "آبشار مارگون",
          "description": "آبشار مارگون در 30 کیلومتری شمال غربی شیراز واقع شده و با ارتفاع 70 متر یکی از بلندترین آبشارهای ایران به شمار می‌آید. این آبشار به دلیل مناظر طبیعی زیبا و محیط سرسبز اطرافش، مقصدی محبوب برای گردشگران است. آبشار مارگون از چشمه‌های زیرزمینی تغذیه می‌شود و به دلیل آب و هوای مطبوع منطقه، زیستگاه مناسبی برای گونه‌های مختلف گیاهی و جانوری است.",
          "vote": [
            {
              "labels": [
                "Acceptable"
              ]
            }
          ]
        },
        {
          "name": "دریاچه ارژن",
          "description": "دریاچه ارژن در 30 کیلومتری شمال غرب شیراز قرار دارد و به عنوان یک تالاب بین‌المللی شناخته می‌شود. این دریاچه به دلیل تنوع زیستی بالا و وجود پرندگان مهاجر، از اهمیت بالایی برخوردار است. دریاچه ارژن به عنوان یک منبع آبی برای کشاورزی و همچنین یک منطقه گردشگری طبیعی محسوب می‌شود.",
          "vote": [
            {
              "labels": [
                "Acceptable"
              ]
            }
          ]
        },
        {
          "name": "چشمه‌های آبگرم پاسارگاد",
          "description": "چشمه‌های آبگرم پاسارگاد در نزدیکی شهر پاسارگاد واقع شده و به دلیل خواص درمانی آب‌های گرم خود شناخته شده‌اند. این چشمه‌ها به عنوان یک جاذبه طبیعی و گردشگری، سالانه میزبان بسیاری از گردشگران و بیماران هستند. آب این چشمه‌ها دارای مواد معدنی مفیدی است که به بهبود بیماری‌های پوستی و مفصلی کمک می‌کند.",
          "vote": [
            {
              "labels": [
                "Acceptable"
              ]
            }
          ]
        },
        {
          "name": "رودخانه پریشان",
          "description": "رودخانه پریشان یکی از رودخانه‌های مهم استان فارس است که از کوه‌های زاگرس سرچشمه می‌گیرد و به سمت دریاچه پریشان جریان دارد. این رودخانه به عنوان منبع آب برای کشاورزی و تأمین آب شرب مناطق اطراف شناخته می‌شود. همچنین، وجود این رودخانه به تنوع زیستی منطقه و اکوسیستم‌های اطراف آن کمک می‌کند.",
          "vote": [
            {
              "labels": [
                "Acceptable"
              ]
            }
          ]
        },
        {
          "name": "چشمه آب معدنی ساسان",
          "description": "چشمه آب معدنی ساسان در 50 کیلومتری شمال شرقی شیراز واقع شده و به دلیل خواص درمانی آب آن، مورد توجه گردشگران و درمان‌جویان قرار دارد. این چشمه به عنوان یکی از منابع آبی مهم استان فارس، در بهبود بیماری‌های مختلف مؤثر است و محیطی آرام و دلنشین برای بازدیدکنندگان فراهم می‌آورد.",
          "vote": [
            {
              "labels": [
                "Acceptable"
              ]
            }
          ]
        },
        {
          "name": "دریاچه پریشان",
          "description": "دریاچه پریشان در نزدیکی شهرستان کازرون قرار دارد و به عنوان یک تالاب طبیعی شناخته می‌شود. این دریاچه به دلیل تنوع زیستی و وجود پرندگان مهاجر، از اهمیت بالایی برخوردار است. همچنین، دریاچه پریشان به عنوان منبع آب برای کشاورزی و تأمین آب شرب مناطق اطراف مورد استفاده قرار می‌گیرد.",
          "vote": [
            {
              "labels": [
                "Acceptable"
              ]
            }
          ]
        },
        {
          "name": "آبشار تنگه رغز",
          "description": "آبشار تنگه رغز در 40 کیلومتری شمال غربی شیراز واقع شده و با ارتفاعی حدود 30 متر، یکی از آبشارهای زیبا و طبیعی استان فارس به شمار می‌آید. این آبشار به دلیل محیط طبیعی و مناظر دیدنی اطرافش، مقصدی محبوب برای گردشگران است. آبشار تنگه رغز از چشمه‌های زیرزمینی تغذیه می‌شود و به عنوان یک منبع آبی مهم برای منطقه محسوب می‌شود.",
          "vote": [
            {
              "labels": [
                "Acceptable"
              ]
            }
          ]
        },
        {
          "name": "چشمه آب معدنی خفر",
          "description": "چشمه آب معدنی خفر در شهرستان خفر واقع شده و به دلیل خواص درمانی آب آن، مورد توجه بسیاری از افراد قرار دارد. این چشمه به عنوان یکی از منابع آبی مهم استان فارس، در بهبود بیماری‌های مختلف مؤثر است و محیطی آرام و دلنشین برای بازدیدکنندگان فراهم می‌آورد.",
          "vote": [
            {
              "labels": [
                "Acceptable"
              ]
            }
          ]
        }
      ]
    }
  ],
  "tourist_attractions": [
    [
      {
        "name": "تخت جمشید",
        "images": [
          "https://upload.wikimedia.org/wikipedia/commons/thumb/3/39/Gate_of_All_Nations%2C_Persepolis.jpg/500px-Gate_of_All_Nations%2C_Persepolis.jpg"
        ],
        "year_built": "518 قبل از میلاد",
        "architect": "داریوش یکم",
        "constructor": "هخامنشیان",
        "description": "تخت جمشید یا پرسپولیس، پایتخت هخامنشیان در دوران باستان است. این مکان در 50 کیلومتری شمال شیراز واقع شده و به عنوان یکی از بزرگ‌ترین و مهم‌ترین آثار باستانی ایران شناخته می‌شود. طراحی آن شامل مجموعه‌ای از کاخ‌ها و بناهای عظیم است که نمایانگر شکوه و عظمت امپراتوری هخامنشی است. تخت جمشید در سال 1979 به عنوان میراث جهانی یونسکو ثبت شده است.",
        "vote": [
          {
            "labels": [
              "Acceptable"
            ]
          }
        ]
      },
      {
        "name": "آرامگاه حافظ",
        "images": [
          "https://upload.wikimedia.org/wikipedia/commons/thumb/d/df/Hafez_shirazi_07.jpg/500px-Hafez_shirazi_07.jpg"
        ],
        "year_built": "قرن 14 میلادی",
        "architect": "آندره گدار",
        "constructor": "وزارت فرهنگ و ارشاد اسلامی ایران",
        "description": "آرامگاه حافظ، شاعر بزرگ ایرانی، در شیراز واقع شده و یکی از مهم‌ترین جاذبه‌های گردشگری این شهر است. این مکان به‌عنوان نمادی از فرهنگ و ادب ایرانی شناخته می‌شود و سالانه میزبان هزاران گردشگر داخلی و خارجی است. معماری آرامگاه، شامل یک گنبد زیبا و باغی دل‌انگیز است که فضایی آرامش‌بخش را فراهم می‌کند.",
        "vote": [
          {
            "labels": [
              "Acceptable"
            ]
          }
        ]
      },
      {
        "name": "آرامگاه سعدی",
        "images": [
          "https://upload.wikimedia.org/wikipedia/commons/thumb/c/cf/Tomb_of_Persian_poet_Sadi_of_Shiraz2.jpg/500px-Tomb_of_Persian_poet_Sadi_of_Shiraz2.jpg"
        ],
        "year_built": "قرن 13 میلادی",
        "architect": "آندره گدار",
        "constructor": "وزارت فرهنگ و ارشاد اسلامی ایران",
        "description": "آرامگاه سعدی، شاعر و نویسنده بزرگ ایرانی، در شیراز واقع شده است. این مکان به‌عنوان یک مرکز فرهنگی و ادبی شناخته می‌شود و دارای باغی زیبا و معماری خاصی است که نشان‌دهنده هنر ایرانی است. آرامگاه سعدی به‌عنوان یکی از جاذبه‌های مهم گردشگری در شیراز، سالانه پذیرای بازدیدکنندگان زیادی است.",
        "vote": [
          {
            "labels": [
              "Acceptable"
            ]
          }
        ]
      },
      {
        "name": "باغ ارم",
        "images": [
          "https://upload.wikimedia.org/wikipedia/commons/thumb/b/bb/Eram%2C_Shiraz%2C_Fars_Province%2C_Iran_-_panoramio_%282%29.jpg/500px-Eram%2C_Shiraz%2C_Fars_Province%2C_Iran_-_panoramio_%282%29.jpg"
        ],
        "year_built": "قرن 19 میلادی",
        "architect": "حاج محمدحسن معمار",
        "constructor": "قاجاریان",
        "description": "باغ ارم یکی از زیباترین باغ‌های ایرانی در شیراز است که به‌عنوان نماد باغ‌های ایرانی شناخته می‌شود. این باغ با طراحی خاص خود، شامل درختان میوه، گل‌های رنگارنگ و آب‌نماهایی زیبا است. باغ ارم به‌عنوان میراث جهانی یونسکو ثبت شده و سالانه میزبان گردشگران زیادی است.",
        "vote": [
          {
            "labels": [
              "Acceptable"
            ]
          }
        ]
      },
      {
        "name": "مسجد نصیرالملک",
        "images": [
          "https://upload.wikimedia.org/wikipedia/commons/thumb/c/c1/%D9%86%D9%85%D8%A7%DB%8C_%DA%A9%D9%84%DB%8C_%D9%85%D8%B3%D8%AC%D8%AF.jpg/500px-%D9%86%D9%85%D8%A7%DB%8C_%DA%A9%D9%84%DB%8C_%D9%85%D8%B3%D8%AC%D8%AF.jpg"
        ],
        "year_built": "قرن 19 میلادی",
        "architect": "محمدحسن معمار",
        "constructor": "میرزا حسن علی خان",
        "description": "مسجد نصیرالملک که به مسجد صورتی نیز معروف است، یکی از زیباترین مساجد شیراز است. این مسجد به خاطر شیشه‌های رنگی و معماری خاصش شناخته می‌شود. نورهای رنگی که از شیشه‌ها به داخل مسجد می‌تابد، فضایی جادویی و زیبا ایجاد می‌کند. این مسجد به‌عنوان یکی از جاذبه‌های اصلی گردشگری در شیراز محسوب می‌شود.",
        "vote": [
          {
            "labels": [
              "Acceptable"
            ]
          }
        ]
      },
      {
        "name": "باغ عفیف‌آباد",
        "images": [
          "https://upload.wikimedia.org/wikipedia/commons/thumb/c/c1/%D9%86%D9%85%D8%A7%DB%8C_%DA%A9%D9%84%DB%8C_%D9%85%D8%B3%D8%AC%D8%AF.jpg/500px-%D9%86%D9%85%D8%A7%DB%8C_%DA%A9%D9%84%DB%8C_%D9%85%D8%B3%D8%AC%D8%AF.jpg"
        ],
        "year_built": "قرن 19 میلادی",
        "architect": "معماران قاجاری",
        "constructor": "قاجاریان",
        "description": "باغ عفیف‌آباد یکی از باغ‌های تاریخی شیراز است که به سبک باغ‌های ایرانی طراحی شده است. این باغ دارای درختان کهن، حوض‌ها و عمارت‌های زیبایی است که به‌عنوان یک مکان تفریحی و گردشگری شناخته می‌شود. باغ عفیف‌آباد همچنین شامل موزه‌ای از سلاح‌های قدیمی و آثار تاریخی است.",
        "vote": [
          {
            "labels": [
              "Acceptable"
            ]
          }
        ]
      },
      {
        "name": "باغ شاهزاده",
        "images": [],
        "year_built": "قرن 19 میلادی",
        "architect": "معماران قاجاری",
        "constructor": "قاجاریان",
        "description": "باغ شاهزاده، واقع در نزدیکی شیراز، یکی از باغ‌های زیبا و تاریخی ایران است. این باغ به‌عنوان یک مکان تفریحی و گردشگری شناخته می‌شود و دارای درختان میوه، گل‌ها و آب‌نماهایی زیبا است. باغ شاهزاده به‌عنوان نمادی از هنر باغ‌سازی ایرانی محسوب می‌شود.",
        "vote": [
          {
            "labels": [
              "Needs Revision"
            ]
          }
        ]
      },
      {
        "name": "قلعه دختر",
        "images": [
          "https://upload.wikimedia.org/wikipedia/commons/5/5d/Ghaledokhtar_Firuzabad_Fars.jpg"
        ],
        "year_built": "قرن 3 میلادی",
        "architect": "اردشیر یکم",
        "constructor": "اردشیر یکم",
        "description": "قلعه دختر، واقع در نزدیکی شیراز، یکی از آثار تاریخی و باستانی ایران است. این قلعه به‌عنوان یک دژ دفاعی در دوران باستان ساخته شده و دارای معماری خاصی است. قلعه دختر به‌عنوان یکی از جاذبه‌های گردشگری در شیراز، سالانه میزبان بازدیدکنندگان زیادی است.",
        "vote": [
          {
            "labels": [
              "Acceptable"
            ]
          }
        ]
      },
      {
        "name": "آبشار مارگون",
        "images": [
          "https://upload.wikimedia.org/wikipedia/commons/8/80/Margoon_Waterfall_%281%29.jpg"
        ],
        "year_built": null,
        "architect": null,
        "constructor": null,
        "description": "آبشار مارگون، واقع در نزدیکی شیراز، یکی از زیباترین آبشارهای ایران است. این آبشار با ارتفاع 70 متر، به‌عنوان یکی از جاذبه‌های طبیعی استان فارس شناخته می‌شود. آبشار مارگون در فصل‌های بهار و تابستان، به‌خصوص زیبا و دیدنی است و سالانه گردشگران زیادی را جذب می‌کند.",
        "vote": [
          {
            "labels": [
              "Acceptable"
            ]
          }
        ]
      },
      {
        "name": "غار سنگ‌تراشان",
        "images": [
          "https://upload.wikimedia.org/wikipedia/commons/9/99/Sangshekan.JPG"
        ],
        "year_built": null,
        "architect": null,
        "constructor": null,
        "description": "غار سنگ‌تراشان، واقع در نزدیکی شیراز، یکی از جاذبه‌های طبیعی و تاریخی استان فارس است. این غار به‌عنوان محل کار سنگ‌تراشان در دوران باستان شناخته می‌شود و دارای آثار باستانی و سنگ‌نگاره‌های منحصر به فردی است. غار سنگ‌تراشان به‌عنوان یک مکان گردشگری، سالانه بازدیدکنندگان زیادی را جذب می‌کند.",
        "vote": [
          {
            "labels": [
              "Acceptable"
            ]
          }
        ]
      },
      {
        "name": "مسجد جامع عتیق",
        "images": [
          "https://upload.wikimedia.org/wikipedia/commons/5/58/Masjed_jame_Atigh_shiraz.jpg"
        ],
        "year_built": "قرن 9 میلادی",
        "architect": "عمرو بن لیث صفاری",
        "constructor": "صفاریان",
        "description": "مسجد جامع عتیق، واقع در مرکز شیراز، یکی از قدیمی‌ترین مساجد ایران است. این مسجد به‌عنوان نمونه‌ای از معماری اسلامی در ایران شناخته می‌شود و دارای تزئینات و کاشی‌کاری‌های زیبا است. مسجد جامع عتیق به‌عنوان یک مکان تاریخی و مذهبی، سالانه میزبان بازدیدکنندگان زیادی است.",
        "vote": [
          {
            "labels": [
              "Acceptable"
            ]
          }
        ]
      },
      {
        "name": "آبشار و تنگه بستانک",
        "images": [],
        "year_built": null,
        "architect": null,
        "constructor": null,
        "description": "آبشار و تنگه بستانک، واقع در نزدیکی شیراز، یکی از جاذبه‌های طبیعی استان فارس است. این منطقه با مناظر طبیعی زیبا و آبشارهای خروشان، به‌عنوان یک مکان تفریحی و گردشگری شناخته می‌شود. آبشار و تنگه بستانک در فصل‌های بهار و تابستان، به‌خصوص زیبا و دیدنی است.",
        "vote": [
          {
            "labels": [
              "Needs Revision"
            ]
          }
        ]
      },
      {
        "name": "تنگه رغز",
        "images": [
          "https://upload.wikimedia.org/wikipedia/commons/thumb/3/39/Raghezdarab.jpg/1200px-Raghezdarab.jpg"
        ],
        "year_built": null,
        "architect": null,
        "constructor": null,
        "description": "تنگه رغز، واقع در نزدیکی شیراز، یکی از جاذبه‌های طبیعی و گردشگری استان فارس است. این تنگه با مناظر طبیعی زیبا و دیواره‌های سنگی، به‌عنوان یک مکان مناسب برای کوهنوردی و پیاده‌روی شناخته می‌شود. تنگه رغز به‌عنوان یکی از مناطق بکر و دست‌نخورده طبیعی، سالانه گردشگران زیادی را جذب می‌کند.",
        "vote": [
          {
            "labels": [
              "Acceptable"
            ]
          }
        ]
      },
      {
        "name": "دریاچه مهارلو",
        "images": [
          "https://upload.wikimedia.org/wikipedia/commons/thumb/f/fa/Maharloo_Lake%2C_Iran_ESA23463799.jpeg/960px-Maharloo_Lake%2C_Iran_ESA23463799.jpeg"
        ],
        "year_built": null,
        "architect": null,
        "constructor": null,
        "description": "دریاچه مهارلو، واقع در نزدیکی شیراز، یکی از دریاچه‌های طبیعی و زیبا در استان فارس است. این دریاچه به‌عنوان یک زیستگاه طبیعی برای پرندگان مهاجر شناخته می‌شود و دارای منظره‌ای زیبا و آرامش‌بخش است. دریاچه مهارلو به‌عنوان یک مکان تفریحی و گردشگری، سالانه بازدیدکنندگان زیادی را جذب می‌کند.",
        "vote": [
          {
            "labels": [
              "Acceptable"
            ]
          }
        ]
      },
      {
        "name": "باغ دلگشا",
        "images": [
          "https://upload.wikimedia.org/wikipedia/commons/9/97/Delgosha_Garden_01.JPG"
        ],
        "year_built": "قرن 18 میلادی",
        "architect": "معماران زندیه",
        "constructor": "زندیه",
        "description": "باغ دلگشا، واقع در شیراز، یکی از باغ‌های تاریخی و زیبا در ایران است. این باغ به‌عنوان نمادی از باغ‌سازی ایرانی شناخته می‌شود و دارای درختان میوه، گل‌ها و آب‌نماهایی زیبا است. باغ دلگشا به‌عنوان یک مکان تفریحی و گردشگری، سالانه پذیرای بازدیدکنندگان زیادی است.",
        "vote": [
          {
            "labels": [
              "Acceptable"
            ]
          }
        ]
      },
      {
        "name": "مسجد جمعه شیراز",
        "images": [
          "https://upload.wikimedia.org/wikipedia/commons/thumb/5/58/Masjed_jame_Atigh_shiraz.jpg/250px-Masjed_jame_Atigh_shiraz.jpg"
        ],
        "year_built": "قرن 9 میلادی",
        "architect": "عمرو بن لیث صفاری",
        "constructor": "صفاریان",
        "description": "مسجد جمعه شیراز، یکی از قدیمی‌ترین مساجد ایران است که به‌عنوان نمونه‌ای از معماری اسلامی در ایران شناخته می‌شود. این مسجد دارای تزئینات و کاشی‌کاری‌های زیبا است و به‌عنوان یک مکان تاریخی و مذهبی، سالانه میزبان بازدیدکنندگان زیادی است.",
        "vote": [
          {
            "labels": [
              "Acceptable"
            ]
          }
        ]
      },
      {
        "name": "آبشار کوهمره نودان",
        "images": [
          "https://upload.wikimedia.org/wikipedia/commons/1/1f/Kohmare-sorkhi.jpg"
        ],
        "year_built": null,
        "architect": null,
        "constructor": null,
        "description": "آبشار کوهمره نودان، واقع در استان فارس، یکی از جاذبه‌های طبیعی و گردشگری این منطقه است. این آبشار با ارتفاعات بلند و مناظر طبیعی زیبا، به‌عنوان یک مکان مناسب برای طبیعت‌گردی و کوهنوردی شناخته می‌شود.",
        "vote": [
          {
            "labels": [
              "Acceptable"
            ]
          }
        ]
      },
      {
        "name": "غار شاپور",
        "images": [
          "https://otragh.com/wp-content/uploads/2025/04/%D8%B7%D8%B8%D8%B8.jpg"
        ],
        "year_built": null,
        "architect": null,
        "constructor": null,
        "description": "غار شاپور، واقع در نزدیکی شیراز، یکی از غارهای تاریخی و طبیعی ایران است. این غار به‌عنوان محل زندگی انسان‌های اولیه و همچنین محل پرستش در دوران باستان شناخته می‌شود. غار شاپور به‌عنوان یک مکان گردشگری، سالانه بازدیدکنندگان زیادی را جذب می‌کند.",
        "vote": [
          {
            "labels": [
              "Acceptable"
            ]
          }
        ]
      },
      {
        "name": "آبشار تنگه چنار",
        "images": [],
        "year_built": null,
        "architect": null,
        "constructor": null,
        "description": "آبشار تنگه چنار، واقع در نزدیکی شیراز، یکی از جاذبه‌های طبیعی استان فارس است. این آبشار با مناظر طبیعی زیبا و آب‌وهوای مطبوع، به‌عنوان یک مکان مناسب برای تفریح و گردشگری شناخته می‌شود.",
        "vote": [
          {
            "labels": [
              "Needs Revision"
            ]
          }
        ]
      },
      {
        "name": "مسجد وکیل",
        "images": [
          "https://upload.wikimedia.org/wikipedia/commons/b/b3/Vakil_mosque_Panorama.jpg"
        ],
        "year_built": "قرن 18 میلادی",
        "architect": "محمدرضا اصفهانی",
        "constructor": "کریم خان زند",
        "description": "مسجد وکیل، واقع در شیراز، یکی از زیباترین مساجد ایران است. این مسجد به‌عنوان نمونه‌ای از معماری اسلامی و هنر ایرانی شناخته می‌شود و دارای تزئینات و کاشی‌کاری‌های زیبا است. مسجد وکیل به‌عنوان یک مکان تاریخی و مذهبی، سالانه میزبان بازدیدکنندگان زیادی است.",
        "vote": [
          {
            "labels": [
              "Acceptable"
            ]
          }
        ]
      },
      {
        "name": "مقبره کوروش",
        "images": [
          "https://upload.wikimedia.org/wikipedia/commons/5/51/Pasargad_Tomb_Cyrus3.jpg"
        ],
        "year_built": "قرن 6 قبل از میلاد",
        "architect": "کوروش بزرگ",
        "constructor": "هخامنشیان",
        "description": "مقبره کوروش، واقع در پاسارگاد، یکی از مهم‌ترین آثار تاریخی ایران است. این مقبره به‌عنوان محل دفن کوروش بزرگ، بنیان‌گذار امپراتوری هخامنشی شناخته می‌شود و به‌عنوان نمادی از تاریخ و فرهنگ ایران محسوب می‌شود.",
        "vote": [
          {
            "labels": [
              "Acceptable"
            ]
          }
        ]
      },
      {
        "name": "پاسارگاد",
        "images": [
          "https://upload.wikimedia.org/wikipedia/commons/5/51/Pasargad_Tomb_Cyrus3.jpg"
        ],
        "year_built": "قرن 6 قبل از میلاد",
        "architect": "کوروش بزرگ",
        "constructor": "هخامنشیان",
        "description": "پاسارگاد، پایتخت نخستین امپراتوری ایران به‌دست کوروش بزرگ، یکی از مهم‌ترین آثار باستانی ایران است. این سایت شامل مقبره کوروش، باغ‌های ایرانی و دیگر بناهای تاریخی است. پاسارگاد به‌عنوان میراث جهانی یونسکو ثبت شده و سالانه گردشگران زیادی را به خود جذب می‌کند.",
        "vote": [
          {
            "labels": [
              "Acceptable"
            ]
          }
        ]
      },
      {
        "name": "غار کلماکره",
        "images": [],
        "year_built": null,
        "architect": null,
        "constructor": null,
        "description": "غار کلماکره، واقع در نزدیکی شیراز، یکی از غارهای طبیعی و تاریخی ایران است. این غار به‌عنوان محل زندگی انسان‌های اولیه شناخته می‌شود و دارای آثار باستانی و سنگ‌نگاره‌های منحصر به فردی است.",
        "vote": [
          {
            "labels": [
              "Needs Revision"
            ]
          }
        ]
      },
      {
        "name": "دریاچه پریشان",
        "images": [
          "https://upload.wikimedia.org/wikipedia/commons/thumb/2/28/%D8%AF%D8%B1%D9%8A%D8%A7%DA%86%D9%87_%D9%BE%D8%B1%D9%8A%D8%B4%D8%A7%D9%86_parishan_lake_-_panoramio.jpg/1200px-%D8%AF%D8%B1%D9%8A%D8%A7%DA%86%D9%87_%D9%BE%D8%B1%D9%8A%D8%B4%D8%A7%D9%86_parishan_lake_-_panoramio.jpg"
        ],
        "year_built": null,
        "architect": null,
        "constructor": null,
        "description": "دریاچه پریشان، واقع در استان فارس، یکی از دریاچه‌های طبیعی و زیبا در ایران است. این دریاچه به‌عنوان یک زیستگاه طبیعی برای پرندگان مهاجر شناخته می‌شود و دارای منظره‌ای زیبا و آرامش‌بخش است.",
        "vote": [
          {
            "labels": [
              "Acceptable"
            ]
          }
        ]
      },
      {
        "name": "قلعه اژدهاپیکر",
        "images": [
          "https://mahjan.ir/portals/0/gh1.gif?ver=NdTtm3GkftpOKQaJ30toBw%3D%3D"
        ],
        "year_built": null,
        "architect": null,
        "constructor": null,
        "description": "قلعه اژدهاپیکر، واقع در استان فارس، یکی از آثار تاریخی و باستانی ایران است. این قلعه به‌عنوان یک دژ دفاعی در دوران باستان ساخته شده و دارای معماری خاصی است. قلعه اژدهاپیکر به‌عنوان یکی از جاذبه‌های گردشگری در فارس، سالانه میزبان بازدیدکنندگان زیادی است.",
        "vote": [
          {
            "labels": [
              "Acceptable"
            ]
          }
        ]
      },
      {
        "name": "آبشار بیدزرد",
        "images": [],
        "year_built": null,
        "architect": null,
        "constructor": null,
        "description": "آبشار بیدزرد، واقع در استان فارس، یکی از جاذبه‌های طبیعی و گردشگری این منطقه است. این آبشار با مناظر طبیعی زیبا و آب‌وهوای مطبوع، به‌عنوان یک مکان مناسب برای تفریح و گردشگری شناخته می‌شود.",
        "vote": [
          {
            "labels": [
              "Needs Revision"
            ]
          }
        ]
      },
      {
        "name": "غار قوری قلعه",
        "images": [],
        "year_built": null,
        "architect": null,
        "constructor": null,
        "description": "غار قوری قلعه، واقع در نزدیکی شیراز، یکی از غارهای طبیعی و تاریخی ایران است. این غار به‌عنوان محل زندگی انسان‌های اولیه شناخته می‌شود و دارای آثار باستانی و سنگ‌نگاره‌های منحصر به فردی است.",
        "vote": [
          {
            "labels": [
              "Needs Revision"
            ]
          }
        ]
      },
      {
        "name": "بازار وکیل",
        "images": [
          "https://upload.wikimedia.org/wikipedia/commons/thumb/1/19/Bazar_vakil_shiraz9.JPG/1200px-Bazar_vakil_shiraz9.JPG"
        ],
        "year_built": "حدود ۱۲۱۰ هجری قمری",
        "architect": "کریم خان زند",
        "constructor": "کریم خان زند",
        "description": "بازار وکیل یکی از مهم‌ترین و تاریخی‌ترین بازارهای شیراز است که در زمان کریم‌خان زند ساخته شده است. این بازار به عنوان یک مرکز تجاری و فرهنگی در شیراز شناخته می‌شود و دارای معماری خاص و زیبا با سقف‌های گنبدی و حجره‌های متعدد است. بازار وکیل به دلیل موقعیت جغرافیایی‌اش در مرکز شهر، اهمیت بالایی در تبادل کالا و فرهنگ داشته و همچنان یکی از مقاصد اصلی گردشگران است.",
        "vote": [
          {
            "labels": [
              "Acceptable"
            ]
          }
        ]
      }
    ]
  ],
  "additional_info": {
    "books_source": "http://chap.sch.ir/category/دوره-آموزش-متوسطه/جغرافیای-استان‌ها",
    "online_resources": [
      "https://fa.wikipedia.org/wiki/استان_فارس",
      "https://fa.wikipedia.org/wiki/فهرست_شهرستان‌های_استان_فارس",
      "https://www.kojaro.com/fars/",
      "https://www.kojaro.com/shiraz/",
      "https://lastsecond.ir/attractions/fars-province",
      "https://lastsecond.ir/fars-province",
      "https://www.karnaval.ir/things-to-do/list-fars-province",
      "https://www.karnaval.ir/things-to-do/list-fars-province/the-best-nature-tourism-destinations-in-fars",
      "https://ghasedak24.com/mag/experience/fars-attractions/",
      "https://www.alibaba.ir/mag/fars/shiraz/shiraz-attractions/",
      "https://arandtour.com/news.cfm?id=2237",
      "https://hotelato.ir/gds/fa/mag/shiraz-waterfalls",
      "https://seeiran.ir/10-%D8%AC%D8%A7%DB%8C-%D8%AF%DB%8C%D8%AF%D9%86%DB%8C-%D8%B4%DB%8C%D8%B1%D8%A7%D8%B2-%D8%AF%D8%B1-%D8%AA%D8%A7%D8%A8%D8%B3%D8%AA/",
      "https://seeiran.ir/tag/%D8%AC%D8%A7%D9%87%D8%A7%DB%8C-%D8%AF%DB%8C%D8%AF%D9%86%DB%8C-%D9%81%D8%A7%D8%B1%D8%B3/",
      "https://seeiran.ir/category/states/fars/shiraz/",
      "https://fafarschto.ir/",
      "https://farschto.ir/",
      "https://radiogardesh.com/sights-of-fars/",
      "https://www.flytoday.ir/blog/fars-province-attractions/",
      "https://safarmarket.com/blog/shiraz-travel-guide",
      "https://blog.safartop.com/travel-guide/places-to-visit-in-shiraz/",
      "https://blog.flysepehran.com/fa/attractions/shiraz-tourist-attractions/",
      "https://kojaplus.ir/%D8%B3%D9%81%D8%B1-3-%D8%B1%D9%88%D8%B2%D9%87-%D8%A8%D9%87-%D8%B4%DB%8C%D8%B1%D8%A7%D8%B2/",
      "https://aminmana.com/tracks/shiraz1/"
    ]
  }
}