{
  "title": "ویژگی‌های جغرافیایی بوشهر",
  "location": {
    "province": "بوشهر",
    "city": "بوشهر"
  },
  "geographical_features": [
{
  "name": "رودخانه‌ها",
  "description": [
    {
      "name": "رودخانه مند",
      "images": [
        "https://yaldamedtour.com/images/content-image/2021/01/iranwatching-1898-1610838716-mand-river-.jpg"
      ],
      "description": "رودخانه مند با طول حدود 725 کیلومتر از ارتفاعات زاگرس سرچشمه گرفته و پس از عبور از شونبه، طسوج، کاکی و بردخون به خلیج فارس می‌ریزد."
    },
    {
      "name": "رودخانه شاپور",
      "images": [
        "https://upload.wikimedia.org/wikipedia/commons/7/77/Shapur_River_of_Kazerun.jpg"
      ],
      "description": "رودخانه شاپور از کوه‌های دشتی سرچشمه گرفته و به خلیج فارس می‌ریزد. طول آن حدود 100 کیلومتر است و برای کشاورزی و آبزی‌پروری اهمیت دارد."
    },
    {
      "name": "رودخانه حله",
      "images": [
        "https://fa.wikipedia.org/wiki/%D8%B1%D9%88%D8%AF_%D8%AD%D9%84%D9%87#/media/%D9%BE%D8%B1%D9%88%D9%86%D8%AF%D9%87:%D8%B1%D9%88%D8%AF_%D8%AD%D9%84%D9%87_%D8%AF%D8%B1_%D9%88%D8%B1%D9%88%D8%AF%DB%8C_%D8%B4%D9%87%D8%B1_%D8%A2%D8%A8%D9%BE%D8%AE%D8%B4.jpg"
      ],
      "description": "رودخانه حله با مساحت حوضهٔ 3210 کیلومتر مربع و طول حدود 80 کیلومتر از دشتی می‌گذرد و به خلیج فارس می‌ریزد."
    },
    {
      "name": "رودخانه خورموج",
      "images": [],
      "description": "رودخانه خورموج در شهرستان دشتی از ارتفاعات زاگرس سرچشمه می‌گیرد و طول آن حدود 70 کیلومتر است."
    },
    {
      "name": "رودخانه گناوه",
      "images": [],
      "description": "رودخانه گناوه در شمال غرب استان قرار دارد و طول آن حدود 50 کیلومتر است."
    },
    {
      "name": "رودخانه دالکی",
      "images": [
        "https://upload.wikimedia.org/wikipedia/commons/4/4a/Bushehr_-_Dalaki_River_-_panoramio.jpg"
      ],
      "description": "رودخانه دالکی در شهرستان دشتستان با طول حدود 40 کیلومتر از کوه‌های زاگرس سرچشمه می‌گیرد."
    }
  ]
},
[
  {
    "name": "کوه‌ها",
    "description": [
      {
        "name": "کوه بیرمی",
        "images": [
          "https://upload.wikimedia.org/wikipedia/commons/0/02/%D8%A8%D8%B1%D9%81_%D8%A8%D8%B1_%D8%B1%D9%88%DB%8C_%DA%A9%D9%88%D9%87_%D8%A8%DB%8C%D8%B1%D9%85%DB%8C.%DA%AF%D8%B4%DB%8C_-_panoramio.jpg"
        ],
        "description": "کوه بیرمی (خورموج) با ارتفاع 1950 متر بلندترین قله استان در شهرستان دشتی است."
      },
      {
        "name": "کوه گیسکان",
        "images": ["https://deyaremehr.ir/wp-content/uploads/2016/03/IMG-20160304-WA0011-Copy.jpg"],
        "description": "کوه گیسکان با ارتفاع 1420 متر در شرق برازجان واقع شده است."
      },
      {
        "name": "کوه سیاه",
        "images": ["https://cdn.isna.ir/d/off/bushehr/2020/04/19/3/61617574.jpg"],
        "description": "کوه سیاه با ارتفاع 1500 متر در دشت‌پلنگ قرار دارد."
      },
      {
        "name": "کوه درنگ",
        "images": ["https://upload.wikimedia.org/wikipedia/fa/8/8d/%DA%A9%D9%88%D9%87_%D8%AF%D8%B1%D9%86%DA%AF_-_%DB%8C%DA%A9.JPG"],
        "description": "کوه درنگ با ارتفاع 1223 متر در شهرستان دیر واقع شده است."
      },
      {
        "name": "کوه احمد سلمان",
        "images": ["https://s0.wklcdn.com/image_367/11034835/124693068/79736811Master.jpg"],
        "description": "کوه احمد سلمان با ارتفاع 1342 متر در شهرستان تنگستان واقع است."
      },
      {
        "name": "کوه کارتنگ",
        "images": [],
        "description": "کوه کارتنگ از رشته مرکزی زاگرس در شمال‌شرق استان بوشهر کشیده شده است."
      },
      {
        "name": "کوه مند",
        "images": ["https://upload.wikimedia.org/wikipedia/commons/6/67/%DA%A9%D9%84%D9%88%D8%AA%E2%80%8C%D9%87%D8%A7%DB%8C_%D9%85%D9%8F%D9%86%D8%AF_-_%D8%A7%D8%B3%D8%AA%D8%A7%D9%86_%D8%A8%D9%88%D8%B4%D9%87%D8%B1.jpg"],
        "description": "کوه مند یکی از ارتفاعات ساحلی استان است که موازات خلیج فارس امتداد یافته."
      },
      {
        "name": "کوه نوکند",
        "images": [],
        "description": "کوه نوکند از ارتفاعات ساحلی استان است که در امتداد ساحل خلیج فارس قرار دارد."
      }
    ]
  },
  {
    "name": "پوشش گیاهی",
    "description": [
      {
        "name": "جنگل‌های حرا",
        "images": [
          "https://upload.wikimedia.org/wikipedia/commons/a/a1/PERSIAN_GULF%2C_Mangrove_jungle_in_Asalouyeh_%D8%AC%D9%86%DA%AF%D9%84_%D8%AD%D8%B1%D8%A7_%D8%8C_%D8%A8%D9%86%D8%AF%D8%B1_%D8%B9%D8%B3%D9%84%D9%88%DB%8C%D9%87_-_panoramio.jpg"
        ],
        "description": "جنگل‌های حرا (مانگرو) در سواحل خلیج فارس در نواحی خورها توسعه یافته‌اند."
      },
      {
        "name": "جنگل‌های نخل",
        "images": [
          "https://upload.wikimedia.org/wikipedia/commons/d/d7/%D9%86%D8%AE%D9%84%D8%B3%D8%AA%D8%A7%D9%86_%DA%AF%D9%86%D8%AF_%D8%B9%D9%84%DB%8C_palm_groves_Gand_Ali_-_panoramio.jpg"
        ],
        "description": "نخلستان‌های استان بوشهر به تولید خرما و اقتصاد محلی کمک می‌کنند."
      },
      {
        "name": "پوشش گیاهی درختان انجیر",
        "images": [
          "https://www.magiran.com/ppic/2835/2535/15-3.jpg"
        ],
        "description": "درختان انجیر در مناطق گرمسیری استان رشد می‌کنند."
      },
      {
        "name": "پوشش گیاهی درختان بومی",
        "images": [],
        "description": "گونه‌های بومی سازگار با اقلیم استان که در حفظ تنوع زیستی نقش دارند."
      },
      {
        "name": "پوشش گیاهی درختان خرما",
        "images": [
          "https://upload.wikimedia.org/wikipedia/commons/d/d7/%D9%86%D8%AE%D9%84%D8%B3%D8%AA%D8%A7%D9%86_%DA%AF%D9%86%D8%AF_%D8%B9%D9%84%DB%8C_palm_groves_Gand_Ali_-_panoramio.jpg"
        ],
        "description": "درختان خرما نقش مهمی در اقتصاد محلی استان دارند."
      },
      {
        "name": "پوشش گیاهی درختان زیتون",
        "images": [
          "https://upload.wikimedia.org/wikipedia/commons/5/5c/Olive_Tree.jpg"
        ],
        "description": "درختان زیتون در نواحی مختلف استان بوشهر رشد می‌کنند."
      },
      {
        "name": "پوشش گیاهی درختان گردو",
        "images": [
          "https://upload.wikimedia.org/wikipedia/commons/2/2a/Walnut_tree.jpg"
        ],
        "description": "درختان گردو یکی دیگر از منابع اقتصادی استان هستند."
      },
      {
        "name": "پوشش گیاهی مرتع",
        "images": [],
        "description": "مرتع‌های استان زیستگاه دام و نقش مهم در اقتصاد محلی دارند."
      },
      {
        "name": "پوشش گیاهی نخلستان‌ها",
        "images": [
          "https://upload.wikimedia.org/wikipedia/commons/d/d7/%D9%86%D8%AE%D9%84%D8%B3%D8%AA%D8%A7%D9%86_%DA%AF%D9%86%D8%AF_%D8%B9%D9%84%DB%8C_palm_groves_Gand_Ali_-_panoramio.jpg"
        ],
        "description": "نخلستان‌ها از منابع مهم اقتصادی استان‌اند."
      },
      {
        "name": "پوشش گیاهی کهور پاکستانی",
        "images": [],
        "description": "کهور پاکستانی گونه‌ای مقاوم به خشکی است."
      },
      {
        "name": "پوشش گیاهی گز",
        "images": [],
        "description": "گز در جلگه‌های ساحلی پراکنده است."
      },
      {
        "name": "جنگل کنار",
        "images": [
          "https://upload.wikimedia.org/wikipedia/commons/a/a1/PERSIAN_GULF%2C_Mangrove_jungle_in_Asalouyeh_%D8%AC%D9%86%DA%AF%D9%84_%D8%AD%D8%B1%D8%A7_%D8%8C_%D8%A8%D9%86%D8%AF%D8%B1_%D8%B9%D8%B3%D9%84%D9%88%DB%8C%D9%87_-_panoramio.jpg"
        ],
        "description": "جامعه گیاهی کنار از مهم‌ترین جوامع جنگلی استان است."
      },
      {
        "name": "جنگل بادام کوهی و بنه",
        "images": [],
        "description": "جامعه گیاهی بادام کوهی و بنه در مناطق کوهستانی دیده می‌شود."
      }
    ]
  }
]

  ],
  "topography": [
    {
      "name": "اقلیم منطقه",
      "description": [
        {
          "name": "آب و هوای بوشهر",
          "description": "استان بوشهر دارای آب و هوای گرم و مرطوب است. این اقلیم تحت تأثیر دریای خلیج فارس قرار دارد و به طور کلی تابستان‌های گرم و زمستان‌های ملایم را تجربه می‌کند. میانگین دما در تابستان به 40 درجه سانتی‌گراد می‌رسد و بارش‌ها عمدتاً در فصل زمستان اتفاق می‌افتد."
        },
        {
          "name": "رطوبت نسبی",
          "description": "رطوبت نسبی در استان بوشهر به طور متوسط بالای 70 درصد است، به ویژه در فصل تابستان. این رطوبت بالا می‌تواند بر روی احساس دما و راحتی ساکنان و گردشگران تأثیر بگذارد و موجب ایجاد شرایط خاصی در زندگی روزمره شود."
        },
        {
          "name": "بادهای موسمی",
          "description": "استان بوشهر تحت تأثیر بادهای موسمی قرار دارد که معمولاً در فصل تابستان شدت بیشتری پیدا می‌کنند. این بادها می‌توانند باعث تغییرات جوی و افزایش رطوبت شوند و بر روی کشاورزی و فعالیت‌های دریایی تأثیرگذار باشند."
        },
        {
          "name": "بارش سالانه",
          "description": "میانگین بارش سالانه در استان بوشهر حدود 300 تا 400 میلی‌متر است که عمدتاً در فصل‌های پاییز و زمستان رخ می‌دهد. این بارش‌ها برای تأمین آب کشاورزی و منابع آبی استان حیاتی هستند."
        },
        {
          "name": "تنوع اقلیمی",
          "description": "استان بوشهر به دلیل موقعیت جغرافیایی و تأثیرات دریایی، دارای تنوع اقلیمی است. این تنوع می‌تواند بر روی نوع پوشش گیاهی و جانوری استان تأثیر بگذارد و به ایجاد زیستگاه‌های مختلف کمک کند."
        }
      ]
    },
    {
      "name": "دشت‌ها و فلات‌ها",
      "description": [
        {
          "name": "دشت لاور",
          "description": "مرکز تولید کشاورزی در دشتی."
        },
        {
          "name": "دشت پلنگ",
          "description": "از دشت‌های مهم شهرستان دشتی."
        },
        {
          "name": "دشت ارم",
          "description": "دشت کشاورزی در شهرستان دشتستان."
        },
        {
          "name": "دشت بوشکان",
          "description": "یکی از دشت‌های مهم شهرستان دشتستان."
        },
        {
          "name": "دشت آبدان",
          "description": "دشت شهرستان دیر."
        },
        {
          "name": "دشت بوشهر",
          "description": "دشت بوشهر یکی از دشت‌های وسیع و حاصلخیز ایران است که به دلیل وجود منابع آبی و خاک مناسب، به کشاورزی و باغداری اختصاص یافته است. این دشت به دلیل موقعیت جغرافیایی‌اش، از نظر اقتصادی و اجتماعی اهمیت ویژه‌ای دارد."
        },
        {
          "name": "فلات بوشهر",
          "description": "فلات بوشهر بخشی از ناحیه کوهستانی زاگرس است که به دلیل ارتفاعات کم و زمین‌های هموار، دارای ویژگی‌های خاصی است. این فلات به عنوان یک منطقه مهم برای کشاورزی و دامداری شناخته می‌شود."
        },
        {
          "name": "دشت‌های ساحلی",
          "description": "دشت‌های ساحلی بوشهر به دلیل نزدیکی به دریا و وجود خاک‌های شنی و رسی، شرایط مناسبی برای کشت انواع محصولات کشاورزی فراهم می‌کند. این دشت‌ها همچنین به عنوان زیستگاه‌های مهم برای پرندگان مهاجر شناخته می‌شوند."
        },
        {
          "name": "دشت‌های نمکی",
          "description": "دشت‌های نمکی بوشهر به دلیل وجود نمک‌زارها و خاک‌های شور، دارای شرایط خاصی هستند. این دشت‌ها به عنوان منابع معدنی و همچنین زیستگاه‌های خاص برای برخی از گونه‌های گیاهی و جانوری شناخته می‌شوند."
        },
        {
          "name": "دشت‌های کشاورزی",
          "description": "دشت‌های کشاورزی بوشهر به دلیل آب و هوای مناسب و خاک‌های حاصلخیز، به کشت محصولات مختلفی مانند خرما، گندم و جو اختصاص یافته‌اند. این دشت‌ها نقش مهمی در تأمین غذا و اشتغال در استان دارند."
        }
      ]
    },
    {
      "name": "ویژگی‌های زمین‌شناسی",
      "description": [
        {
          "name": "زمین‌شناسی بوشهر",
          "description": "زمین‌شناسی استان بوشهر شامل لایه‌های مختلف سنگی و رسوبی است که به دلیل فعالیت‌های tectonic و فرسایش آب و باد شکل گرفته‌اند. این ویژگی‌ها می‌توانند بر روی منابع طبیعی و زیستگاه‌ها تأثیرگذار باشند."
        },
        {
          "name": "گنبدهای نمکی",
          "description": "گنبدهای نمکی بوشهر به دلیل وجود نمک‌های زیرزمینی و فشارهای تکتونیکی به وجود آمده‌اند. این گنبدها به عنوان منابع معدنی و همچنین به دلیل زیبایی‌های طبیعی‌شان، مورد توجه قرار دارند."
        },
        {
          "name": "کوه‌های زاگرس جنوبی",
          "description": "کوه‌های زاگرس جنوبی در بوشهر به دلیل وجود سنگ‌های آهکی و رسوبی، دارای تنوع زیستی و چشم‌اندازهای طبیعی خاصی هستند. این کوه‌ها به عنوان زیستگاه‌های مهمی برای گونه‌های مختلف جانوری و گیاهی شناخته می‌شوند."
        },
        {
          "name": "پهنه‌های سنگی",
          "description": "پهنه‌های سنگی بوشهر به دلیل وجود سنگ‌های سخت و مقاوم، دارای ویژگی‌های خاصی در زمین‌شناسی هستند. این پهنه‌ها می‌توانند به عنوان منابع معدنی و همچنین به عنوان مناطق گردشگری مورد توجه قرار گیرند."
        },
        {
          "name": "چشمه‌های آب گرم",
          "description": "چشمه‌های آب گرم بوشهر به دلیل فعالیت‌های زمین‌شناسی و وجود منابع حرارتی زیرزمینی به وجود آمده‌اند. این چشمه‌ها به عنوان منابع طبیعی و همچنین به عنوان مقاصد گردشگری شناخته می‌شوند."
        },
        {
          "name": "کوه‌های زاگرس",
          "description": "کوه‌های زاگرس در استان بوشهر به عنوان یکی از مهم‌ترین ویژگی‌های زمین‌شناسی این منطقه شناخته می‌شوند. این کوه‌ها به طول تقریبی 1500 کیلومتر و عرض متغیر، از شمال غربی ایران تا جنوب کشور کشیده شده‌اند. این رشته کوه‌ها دارای قله‌های مرتفع و دره‌های عمیق هستند که به تنوع زیستی و اکوسیستم‌های مختلف کمک می‌کنند. از ویژگی‌های جغرافیایی این کوه‌ها می‌توان به وجود کانی‌های مختلف، چشمه‌های آب گرم و تنوع گیاهی اشاره کرد. این کوه‌ها همچنین به عنوان یک منبع آب زیرزمینی برای مناطق اطراف عمل می‌کنند."
        },
        {
          "name": "دشت بوشهر",
          "description": "دشت بوشهر یکی از دشت‌های وسیع و حاصلخیز استان بوشهر است که در آن زمین‌های کشاورزی و منابع آب زیرزمینی فراوانی وجود دارد. این دشت به دلیل موقعیت جغرافیایی و اقلیمی خاص خود، برای کشت محصولات زراعی مانند گندم و جو بسیار مناسب است. دشت بوشهر همچنین به عنوان یک زیستگاه برای گونه‌های مختلف گیاهی و جانوری شناخته می‌شود و به حفظ تنوع زیستی کمک می‌کند."
        },
        {
          "name": "غارهای طبیعی",
          "description": "غارهای طبیعی در استان بوشهر به عنوان یکی از پدیده‌های زمین‌شناسی منحصر به فرد شناخته می‌شوند. این غارها با تشکیل بر اثر فرسایش سنگ‌ها و فعالیت‌های زمین‌شناسی در طول میلیون‌ها سال ایجاد شده‌اند. برخی از این غارها در مناطق کوهستانی قرار دارند و به عنوان جاذبه‌های گردشگری و زیستگاه‌هایی برای گونه‌های خاص جانوری عمل می‌کنند. ویژگی‌های خاص این غارها شامل stalactites و stalagmites است که به زیبایی آن‌ها افزوده است."
        },
        {
          "name": "تپه‌های باستانی",
          "description": "تپه‌های باستانی در استان بوشهر نشان‌دهنده تاریخچه فرهنگی و تمدنی این منطقه هستند. این تپه‌ها معمولاً محل‌های سکونت قدیمی و آثار باستانی از دوره‌های مختلف تاریخی را در خود جای داده‌اند. بررسی این تپه‌ها می‌تواند اطلاعات ارزشمندی درباره زندگی انسان‌ها در دوران‌های گذشته ارائه دهد و به پژوهشگران در زمینه باستان‌شناسی کمک کند."
        },
        {
          "name": "خلیج فارس",
          "description": " خلیج فارس به عنوان یک ویژگی طبیعی مهم در استان بوشهر شناخته می‌شود. این خلیج با آب‌های گرم و شور خود، زیستگاه‌های متنوعی برای انواع موجودات دریایی فراهم می‌آورد. همچنین سواحل بوشهر به دلیل وجود مرجان‌ها و اکوسیستم‌های دریایی، جاذبه‌های گردشگری فراوانی دارند و به عنوان منبع درآمد برای ساکنان محلی عمل می‌کنند."
        }
      ]
    }
  ],
  "natural_resources": [
    {
      "name": "منابع آبی",
      "description": [
        {
          "name": "آب‌های زیرزمینی",
          "description": "چاه، چشمه و قنات‌ها منبع تأمین آب شرب و کشاورزی هستند."
        },
        {
          "name": "چاه‌های آب",
          "description": "چاه‌های عمیق و نیمه‌عمیق استخراج آب زیرزمینی."
        },
        {
          "name": "سواحل و دریا",
          "description": "سواحل خلیج فارس منبع صید و اقتصاد محلی."
        },
        {
          "name": "رودخانه‌های فصلی",
          "description": "فعال در زمان بارش و کمک به کشاورزی."
        },
        {
          "name": "آب‌انبارها",
          "description": "سازه‌های ذخیره‌سازی آب باران و زیرزمینی."
        },
        {
          "name": "سد رئیس علی دلواری",
          "description": "سد واقع بر روی رودخانه شاپور برای تنظیم آب و ذخیره‌سازی."
        }
      ]
    },
    {
      "name": "منابع معدنی",
      "description": [
        {
          "name": "سنگ گچ",
          "description": "استان بوشهر دارای معادن سنگ گچ است که به‌عنوان یکی از منابع معدنی مهم در این استان شناخته می‌شود. سنگ گچ به‌دلیل خواص شیمیایی و فیزیکی خاصش در صنایع ساختمانی و تولید سیمان کاربرد دارد. معادن سنگ گچ در مناطق مختلف استان پراکنده‌اند."
        },
        {
          "name": "نمک",
          "description": "معادن نمک در استان بوشهر به‌عنوان یکی از منابع معدنی با ارزش شناخته می‌شوند. نمک استخراج شده از این معادن به‌عنوان ماده اولیه در صنایع غذایی و شیمیایی کاربرد دارد. وجود معادن نمک در نزدیکی سواحل، دسترسی به این منبع را تسهیل کرده است."
        },
        {
          "name": "معادن سنگ آهن",
          "description": "استان بوشهر دارای معادن سنگ آهن است که به‌عنوان یکی از منابع معدنی با ارزش در تأمین نیازهای صنایع فولاد و متالورژی کشور مورد استفاده قرار می‌گیرد. این معادن به‌ویژه در نواحی کوهستانی استان قرار دارند و استخراج سنگ آهن از آن‌ها به‌دلیل کیفیت بالای سنگ‌ها اهمیت دارد."
        },
        {
          "name": "معادن کلسیت",
          "description": "کلسیت یکی از مواد معدنی موجود در استان بوشهر است که در صنایع ساختمانی و تولید مصالح ساختمانی کاربرد دارد. معادن کلسیت در نواحی مختلف استان وجود دارند و استخراج این ماده معدنی به‌دلیل کاربردهای گسترده‌اش از اهمیت بالایی برخوردار است."
        },
        {
          "name": "معادن خاک نسوز",
          "description": "خاک نسوز یکی از مواد معدنی مهم در استان بوشهر است که در صنایع سرامیک و آجرسازی کاربرد دارد. این معادن به‌دلیل ویژگی‌های خاص خاک نسوز، در تولید محصولات با کیفیت بالا مؤثر هستند و استخراج آن‌ها به‌دلیل تقاضای بالا در بازار، از اهمیت ویژه‌ای برخوردار است."
        }
      ]
    }
  ],
  "tourist_attractions": [
  {
    "name": "ساحل بوشهر",
    "images": ["https://www.mihmansho.com/mag/Files/Root/exteraImage/e310fb36-0edd-40bd-8886-26507062b4f6_mihmansho.jpg"],
    "year_built": null,
    "architect": null,
    "constructor": null,
    "description": "ساحل بوشهر یکی از جاذبه‌های طبیعی و گردشگری این استان است که دارای آب و هوای گرم و مرطوب می‌باشد. این ساحل با طولی به بیش از 20 کیلومتر، مکان مناسبی برای تفریح و آرامش است. در این ساحل می‌توان به فعالیت‌های آبی مانند شنا، قایق‌سواری و ماهیگیری پرداخت. همچنین، وجود رستوران‌ها و کافه‌های متنوع در کنار ساحل، به جذابیت آن افزوده است."
  },
  {
    "name": "جزیره خارک",
    "images": ["https://fa.wikipedia.org/wiki/%D8%AE%D8%A7%D8%B1%DA%AF#/media/%D9%BE%D8%B1%D9%88%D9%86%D8%AF%D9%87:Kharg_Island_in_2022_(07).jpg"],
    "year_built": null,
    "architect": null,
    "constructor": null,
    "description": "جزیره خارک به عنوان یکی از جزایر مهم در استان بوشهر شناخته می‌شود و دارای تاریخچه‌ای غنی و فرهنگی است. این جزیره به دلیل موقعیت جغرافیایی خود، یکی از نقاط استراتژیک برای صادرات نفت به شمار می‌رود. همچنین، دارای سواحل زیبا و آثار باستانی است که گردشگران را به خود جذب می‌کند."
  },
  {
    "name": "قلعه خورموج",
    "images": ["https://fa.wikipedia.org/wiki/%D9%82%D9%84%D8%B9%D9%87_%D8%AE%D9%88%D8%B1%D9%85%D9%88%D8%AC#/media/%D9%BE%D8%B1%D9%88%D9%86%D8%AF%D9%87:GhaleeMohammadKhan.jpg"],
    "year_built": "قرن ۱۹ میلادی (دوره قاجار)",
    "architect": "معماران شیرازی و اصفهانی",
    "constructor": "محمدخان دشتی",
    "description": "قلعه خورموج یکی از آثار تاریخی و مهم استان بوشهر است که در دوران قاجار ساخته شده است. این قلعه به عنوان یک دژ نظامی استفاده می‌شد و دارای معماری خاصی است که نشان‌دهنده هنر و فرهنگ آن زمان می‌باشد. این قلعه در حال حاضر به عنوان یک جاذبه گردشگری مورد توجه قرار گرفته است."
  },
  {
    "name": "گنبد نمکی جاشک",
    "images": ["https://irangard.com/mag/wp-content/uploads/2020/04/Jashak-salt-Bushehr-1.jpg"],
    "year_built": null,
    "architect": null,
    "constructor": null,
    "description": "گنبد نمکی جاشک یکی از عجایب طبیعی استان بوشهر است که به دلیل ویژگی‌های زمین‌شناسی خاص خود، مورد توجه محققان و گردشگران قرار دارد. این گنبد دارای ارتفاعی بالغ بر 200 متر و ترکیبی از نمک و سنگ‌های رسوبی است. همچنین، این منطقه به عنوان یک محل مناسب برای کوهنوردی و طبیعت‌گردی شناخته می‌شود."
  },
  {
    "name": "روستای تاریخی سیراف",
    "images": [
      "https://fa.wikipedia.org/wiki/%D8%B3%DB%8C%D8%B1%D8%A7%D9%81#/media/%D9%BE%D8%B1%D9%88%D9%86%D8%AF%D9%87:Siraf-Wharf.jpg"
    ],
    "year_built": "دوران ساسانی (قرن ۳ میلادی تقریبی)",
    "architect": null,
    "constructor": "ساسانیان",
    "description": "روستای تاریخی سیراف یکی از قدیمی‌ترین و مهم‌ترین مناطق مسکونی در استان بوشهر است. این روستا دارای آثار باستانی فراوانی از جمله خانه‌های قدیمی، مساجد و بازارهای سنتی است. سیراف به عنوان یکی از مراکز تجاری در دوران اسلامی شناخته می‌شود و تاریخچه‌ای غنی از تجارت و فرهنگ را در خود جای داده است."
  },
  {
    "name": "آب‌انبار بوشهر",
    "images": [
      "https://cdn.alibaba.ir/ostorage-ugc/resize/756x450/randd-threepio/6cb0301b74e63a1a759f74941803b4ff33a94b9e829117c2840d10f20468ddbb_original.jpg"
    ],
    "year_built": "۱۲۷۲ قمری (۱۸۵۵ میلادی؛ دوره قاجار)",
    "architect": null,
    "constructor": "حاجی قوام‌الملک",
    "description": "آب‌انبار بوشهر یکی از آثار تاریخی و فرهنگی استان بوشهر است که در گذشته به عنوان منبع تأمین آب شرب استفاده می‌شد. این آب‌انبار با معماری خاص خود و استفاده از مصالح بومی، نشان‌دهنده تکنیک‌های سنتی در ساخت و ساز است. امروزه این آب‌انبار به عنوان یک جاذبه گردشگری مورد بازدید قرار می‌گیرد."
  },
  {
    "name": "پارک ساحلی بوشهر",
    "images": [
      "https://darbushehrkojast.ir/wp-content/uploads/2024/05/Ab-Shirin-Kon-Park-1536x1152.jpg"
    ],
    "year_built": null,
    "architect": null,
    "constructor": null,
    "description": "پارک ساحلی بوشهر یکی از مکان‌های تفریحی و گردشگری این استان است که در کنار دریا واقع شده و فضایی مناسب برای خانواده‌ها و گردشگران فراهم می‌آورد. این پارک دارای امکاناتی چون مسیرهای پیاده‌روی، زمین‌های بازی و رستوران‌ها می‌باشد. همچنین، وجود درختان نخل و فضای سبز، زیبایی خاصی به این پارک بخشیده است."
  },
  {
    "name": "مسجد جامع بوشهر",
    "images": [
      "https://www.eneshat.com/images/2016/11/bardestan-1.jpg"
    ],
    "year_built": "۱۰۱۷ قمری (۱۶۰۸ میلادی؛ دوره صفویه)",
    "architect": null,
    "constructor": "خاندان آل عصفور",
    "description": "مسجد جامع بوشهر یکی از مساجد تاریخی و مهم در استان بوشهر است که در سال ۱۰۱۷ هجری قمری (۱۶۰۸ میلادی) در دوره صفویه توسط خاندان آل عصفور ساخته شده است. این مسجد دارای تزئینات معمارانه و هنری است و به عنوان یک مکان مذهبی و فرهنگی محل تجمع مردم در مناسبت‌های مختلف می‌باشد."
  },
  {
    "name": "جزیره نخیلو",
    "images": ["https://amlakbandarabbas.ir/wp-content/uploads/2024/06/%D8%AC%D8%B2%DB%8C%D8%B1%D9%87-%D9%86%D8%AE%DB%8C%D9%84%D9%88-56384738574.webp"],
    "year_built": null,
    "architect": null,
    "constructor": null,
    "description": "جزیره نخیلو یکی از جزایر کوچک و زیبا در استان بوشهر است که به دلیل سواحل بکر و طبیعت دست‌نخورده‌اش، مورد توجه گردشگران قرار دارد. این جزیره به عنوان مکانی مناسب برای تفریح و استراحت شناخته می‌شود و امکاناتی برای اقامت و تفریحات آبی فراهم کرده است."
  },
  {
    "name": "بندر دیلم",
    "images": [
      "https://upload.wikimedia.org/wikipedia/commons/1/13/Bandar_Deylam_01.jpg"
    ],
    "year_built": null,
    "architect": null,
    "constructor": null,
    "description": "بندر دیلم یکی از شهرهای استان بوشهر است که به دلیل موقعیت جغرافیایی خود در کنار خلیج فارس، دارای سواحل زیبا و امکانات گردشگری متنوعی می‌باشد. این بندر به عنوان یکی از مراکز مهم تجاری و اقتصادی در استان شناخته می‌شود."
  },
  {
    "name": "جزیره شیف",
    "images": [
      "https://fa.wikipedia.org/wiki/%D8%AC%D8%B2%DB%8C%D8%B1%D9%87_%D8%B4%DB%8C%D9%81#/media/%D9%BE%D8%B1%D9%88%D9%86%D8%AF%D9%87:Shif_island,_Iran.jpg"
    ],
    "year_built": null,
    "architect": null,
    "constructor": null,
    "description": "جزیره شیف یکی از جزایر زیبای استان بوشهر است که به دلیل طبیعت بکر و سواحل شنی‌اش، مقصدی محبوب برای گردشگران به شمار می‌رود. این جزیره دارای آب و هوای معتدل و امکانات مناسب برای تفریحات آبی است."
  },
  {
    "name": "بندر کنگان",
    "images": [
      "https://upload.wikimedia.org/wikipedia/commons/2/24/Bandar_Kangan_13960430_03.jpg"
    ],
    "year_built": null,
    "architect": null,
    "constructor": null,
    "description": "بندر کنگان در استان بوشهر واقع شده و به عنوان یکی از بنادر مهم تجاری و نفتی کشور شناخته می‌شود. این بندر دارای سواحل زیبا و امکانات گردشگری متنوعی است که می‌تواند توجه گردشگران را به خود جلب کند."
  },
  {
    "name": "بندر بوشهر",
    "images": [
      "https://lh3.googleusercontent.com/gps-cs-s/AC9h4noOqRMCw9kKeLp4-oOzlN3-MK3bCsokLQ8oexfVYL4dMjkSWKk7Cg6F_rZabvIMEDCCug7VZF55UdgCfxDH9GU8-RLAyUcf7xYThsZz9_C8OpLzIqnbPOiCcXQwcw7npFaxTr8q=w675-h390-n-k-no"
    ],
    "year_built": "۱۱۱۴ خورشیدی (۱۷۳۵ میلادی؛ بنیان بوشهر نو)",
    "architect": null,
    "constructor": "نادرشاه افشار",
    "description": "بندر بوشهر به عنوان یکی از مهم‌ترین بنادر ایران در خلیج فارس، دارای تاریخچه‌ای غنی و فرهنگی منحصر به فرد است. این بندر به دلیل موقعیت استراتژیک خود، جاذبه‌های گردشگری و تاریخی زیادی دارد."
  },
  {
    "name": "ساحل دیر",
    "images": [
      "https://commons.wikimedia.org/wiki/Special:FilePath/Persian_Gulf%2C_Dayyer_%D8%BA%D8%B1%D9%88%D8%A8_%D8%A8%D9%86%D8%AF%D8%B1_%D8%AF%DB%8C%D8%B1_-_panoramio.jpg"
    ],
    "year_built": null,
    "architect": null,
    "constructor": null,
    "description": "ساحل دیر در استان بوشهر با سواحل شنی و آب‌های زلال خود، مکانی مناسب برای تفریحات آبی و استراحت است. این ساحل به دلیل زیبایی‌های طبیعی و امکانات رفاهی، مورد توجه گردشگران قرار دارد."
  },
  {
    "name": "آبشارهای بوشهر",
    "images": ["https://www.vilajar.com/Dashboard/GetArticleImage/24257"],
    "year_built": null,
    "architect": null,
    "constructor": null,
    "description": "آبشارهای بوشهر به عنوان یکی از جاذبه‌های طبیعی این استان، دارای مناظر زیبا و طبیعی است. این آبشارها به دلیل زیبایی و آرامش خود، مقصدی مناسب برای طبیعت‌گردی به شمار می‌آیند."
  },
  {
    "name": "کوه‌های بوشهر",
    "images": [
          "https://upload.wikimedia.org/wikipedia/commons/0/02/%D8%A8%D8%B1%D9%81_%D8%A8%D8%B1_%D8%B1%D9%88%DB%8C_%DA%A9%D9%88%D9%87_%D8%A8%DB%8C%D8%B1%D9%85%DB%8C.%DA%AF%D8%B4%DB%8C_-_panoramio.jpg"
        ],
    "year_built": null,
    "architect": null,
    "constructor": null,
    "description": "کوه‌های بوشهر با مناظر طبیعی و زیبای خود، مکانی مناسب برای کوهنوردی و طبیعت‌گردی هستند. این کوه‌ها به دلیل تنوع زیستی و زیبایی‌های خاص خود، مورد توجه گردشگران قرار دارند."
  },
  {
    "name": "پارک ملی دریایی نایبند",
    "images": [
      "https://api2.kojaro.com/media/2024-2-1e542d92-ac5b-42f5-8225-b64354d9e76d-67c46117c1067c5ba768a324?w=1200&q=80"
    ],
    "year_built": null,
    "architect": null,
    "constructor": null,
    "description": "پارک ملی دریایی نایبند به عنوان یکی از مناطق حفاظت شده در استان بوشهر، دارای تنوع زیستی و مناظر طبیعی زیبا است. این پارک به دلیل اهمیت زیست‌محیطی و گردشگری، مورد توجه قرار دارد."
  },
  {
    "name": "ساحل بندر گناوه",
    "images": [
      "https://commons.wikimedia.org/wiki/Special:FilePath/%D8%AE%D8%B1%DA%86%D9%86%DA%AF_%D8%B3%D8%A7%D8%AD%D9%84_%D8%A8%D9%88%D8%B4%D9%87%D8%B1_%28%D8%B4%D9%87%D8%B1%D8%B3%D8%AA%D8%A7%D9%86_%DA%AF%D9%86%D8%A7%D9%88%D9%87%29%28%D8%AC%D8%B2%DB%8C%D8%B1%D9%87_%D8%B4%D9%85%D8%A7%D9%84%DB%8C_%D9%88_%D8%AC%D9%86%D9%88%D8%A8%DB%8C%29.jpg"
    ],
    "year_built": null,
    "architect": null,
    "constructor": null,
    "description": "ساحل بندر گناوه با سواحل شنی و زیبای خود، مکانی مناسب برای تفریحات آبی و استراحت است. این ساحل به دلیل امکانات رفاهی و زیبایی‌های طبیعی، مورد توجه گردشگران قرار دارد."
  },
  {
    "name": "جزیره بوموسی",
    "images": [
      "https://commons.wikimedia.org/wiki/Special:FilePath/Abu_Musa_Island_%2815%29.jpg"
    ],
    "year_built": null,
    "architect": null,
    "constructor": null,
    "description": "جزیره بوموسی به عنوان یکی از جزایر استان بوشهر، دارای سواحل زیبا و مناظر طبیعی بکر است. این جزیره به دلیل تنوع زیستی و زیبایی‌های خاص خود، مقصدی مناسب برای گردشگران به شمار می‌آید."
  },
  {
    "name": "بندر عسلویه",
    "images": [
      "https://commons.wikimedia.org/wiki/Special:FilePath/Petrochemical_Complexes_in_Asaluyeh_%289%29.jpg"
    ],
    "year_built": null,
    "architect": null,
    "constructor": null,
    "description": "بندر عسلویه به عنوان یکی از بنادر مهم اقتصادی در استان بوشهر، دارای سواحل زیبا و امکانات گردشگری متنوع است. این بندر به دلیل موقعیت استراتژیک خود، جاذبه‌های گردشگری زیادی دارد."
  },
  {
    "name": "جزیره شیدور",
    "images": [
      "https://commons.wikimedia.org/wiki/Special:FilePath/Shidvar_island-1.jpg"
    ],
    "year_built": null,
    "architect": null,
    "constructor": null,
    "description": "جزیره شیدور به عنوان یکی از جزایر استان بوشهر، دارای سواحل زیبا و مناظر طبیعی بکر است. این جزیره به دلیل تنوع زیستی و زیبایی‌های خاص خود، مقصدی مناسب برای گردشگران به شمار می‌آید."
  },
  {
    "name": "بندر گناوه",
    "images": [
      "https://commons.wikimedia.org/wiki/Special:FilePath/Genave_bushehr.jpg"
    ],
    "year_built": "دوران ساسانی (حدود ۱۵۰۰ سال پیش)",
    "architect": null,
    "constructor": "ساسانیان",
    "description": "بندر گناوه یکی از بنادر مهم استان بوشهر است که به دلیل موقعیت جغرافیایی خود، دارای سواحل زیبا و امکانات گردشگری متنوعی می‌باشد. این بندر به عنوان یکی از مراکز اقتصادی و تجاری در استان شناخته می‌شود."
  },
  {
    "name": "خلیج فارس",
    "images": [
      "https://commons.wikimedia.org/wiki/Special:FilePath/Iran_-_Always_Persian_Gulf_-_%D8%AE%D9%84%DB%8C%D8%AC_%D9%87%D9%85%DB%8C%D8%B4%D9%87_%D9%81%D8%A7%D8%B1%D8%B3_-_panoramio.jpg"
    ],
    "year_built": null,
    "architect": null,
    "constructor": null,
    "description": "خلیج فارس به عنوان یکی از مهم‌ترین مناطق آبی در ایران، دارای سواحل زیبا و جاذبه‌های گردشگری متنوعی است. این منطقه به دلیل موقعیت استراتژیک خود، مورد توجه گردشگران و محققان قرار دارد."
  },
  {
    "name": "موزه بوشهر",
    "images": [
      "https://www.alaedin.travel/Files/blogs/museum-in-bushehr-iran-alaedintravel.jpg"
    ],
    "year_built": "۱۳۸۴ خورشیدی (۲۰۰۵ میلادی)",
    "architect": null,
    "constructor": "سازمان میراث فرهنگی ایران",
    "description": "موزه بوشهر به عنوان یکی از مراکز فرهنگی و تاریخی استان، دارای مجموعه‌ای از آثار باستانی و فرهنگی این منطقه است. این موزه به دلیل ارزش‌های تاریخی و فرهنگی خود، جاذبه‌ای برای گردشگران به شمار می‌آید."
  },
  {
    "name": "دریاچه‌های بوشهر",
    "images": [],
    "year_built": null,
    "architect": null,
    "constructor": null,
    "description": "دریاچه‌های بوشهر به عنوان یکی از جاذبه‌های طبیعی این استان، دارای مناظر زیبا و آرامش‌بخش هستند. این دریاچه‌ها به دلیل تنوع زیستی و زیبایی‌های طبیعی خود، مقصدی مناسب برای طبیعت‌گردی به شمار می‌آیند."
  },
  {
    "name": "ساحل بندر دیلم",
    "images": ["https://upload.wikimedia.org/wikipedia/commons/1/13/Bandar_Deylam_01.jpg"],
    "year_built": null,
    "architect": null,
    "constructor": null,
    "description": "ساحل بندر دیلم با سواحل شنی و زیبای خود، مکانی مناسب برای تفریحات آبی و استراحت است. این ساحل به دلیل امکانات رفاهی و زیبایی‌های طبیعی، مورد توجه گردشگران قرار دارد."
  },
  {
    "name": "غارهای کوه‌های بوشهر",
    "images": ["https://www.shidrokh-travel.ir/fa/user/pic/201563620158___.jpg"],
    "year_built": null,
    "architect": null,
    "constructor": null,
    "description": "غارهای کوه‌های بوشهر به عنوان یکی از جاذبه‌های طبیعی این استان، دارای مناظر زیبا و خاصی هستند. این غارها به دلیل ساختار ویژه خود، مورد توجه محققان و گردشگران قرار دارند."
  },
  {
    "name": "ساحل بندر عسلویه",
    "images": [
      "https://cdn.mashreghnews.ir/d/2022/10/11/4/3609118.jpg?ts=1665474476000"
    ],
    "year_built": null,
    "architect": null,
    "constructor": null,
    "description": "ساحل بندر عسلویه با سواحل شنی و زیبای خود، مکانی مناسب برای تفریحات آبی و استراحت است. این ساحل به دلیل امکانات رفاهی و زیبایی‌های طبیعی، مورد توجه گردشگران قرار دارد."
  },
  {
    "name": "قلعه بردستان",
    "images": ["https://upload.wikimedia.org/wikipedia/commons/2/22/Bardestan_Castle.jpg"],
    "year_built": "دوران های تاریخی پس از اسلام",
    "architect": null,
    "constructor": "آل بویه",
    "description": "قلعه بردستان یکی از آثار تاریخی و فرهنگی استان بوشهر است که در شهرستان دیر واقع شده است. این قلعه به عنوان یکی از نمادهای معماری نظامی در سواحل خلیج فارس شناخته می‌شود. ویژگی‌های بارز آن شامل دیوارهای بلند، برج‌های نگهبانی و موقعیت استراتژیک در کنار دریا است. این قلعه در زمان‌های گذشته به عنوان پایگاهی برای دفاع از سواحل و تجارت دریایی مورد استفاده قرار می‌گرفت."
  },
  {
    "name": "روستای چاهکوتاه",
    "images": ["https://cdn.alibaba.ir/ostorage-ugc/resize/190x140/randd-threepio/fe16533c4c358f7f3434c80a50428c5dff7b82c53a82b50d437a6dac1e69a306_original.jpg"],
    "year_built": null,
    "architect": null,
    "constructor": null,
    "description": "روستای چاهکوتاه به عنوان یکی از روستاهای هدف گردشگری استان بوشهر در بخش مرکزی شهرستان بوشهر شناخته می‌شود."
  },
  {
    "name": "روستای درودگاه",
    "images": ["https://upload.wikimedia.org/wikipedia/commons/5/52/Emamzadeh_Doroudgah.JPG"],
    "year_built": null,
    "architect": null,
    "constructor": null,
    "description": "روستای درودگاه در بخش سعدآباد شهرستان دشتستان به‌عنوان یکی از روستاهای هدف گردشگری استان معرفی شده است."
  },
  {
    "name": "روستای رودفاریاب",
    "images": ["https://fa.tripyar.com/uploads/picture/2432/2.jpg"],
    "year_built": null,
    "architect": null,
    "constructor": null,
    "description": "روستای رودفاریاب در بخش تنگ ارم شهرستان دشتستان یکی از روستاهای هدف گردشگری استان بوشهر است."
  },
  {
    "name": "روستای حصار",
    "images": [
      "https://upload.wikimedia.org/wikipedia/commons/c/cf/Agha_khan_Liravi_Castle_20170330_23.jpg"
    ],
    "year_built": null,
    "architect": null,
    "constructor": null,
    "description": "روستای حصار در بخش امام حسن شهرستان دیلم به‌عنوان یکی از روستاهای هدف گردشگری استان بوشهر شناخته می‌شود."
  },
  {
    "name": "روستای شول",
    "images": [],
    "year_built": null,
    "architect": null,
    "constructor": null,
    "description": "روستای شول در بخش سعدآباد شهرستان دشتستان یکی از روستاهای هدف گردشگری استان بوشهر است."
  },
  {
    "name": "روستای هاله (نای بند)",
    "images": [],
    "year_built": null,
    "architect": null,
    "constructor": null,
    "description": "روستای هاله (نای بند) در بخش چاه مبارک شهرستان عسلویه به‌عنوان یکی از روستاهای هدف گردشگری استان معرفی شده است."
  },
  {
    "name": "روستای گشی (خاییز)",
    "images": [],
    "year_built": null,
    "architect": null,
    "constructor": null,
    "description": "روستای گشی (خاییز) در بخش مرکزی شهرستان تنگستان یکی از روستاهای هدف گردشگری استان بوشهر است."
  },
  {
    "name": "جزیره شمالی",
    "images": [
      "https://upload.wikimedia.org/wikipedia/commons/3/32/%D8%AC%D8%B2%DB%8C%D8%B1%D9%87_%D8%B4%D9%85%D8%A7%D9%84%DB%8C.jpg"],
    "year_built": null,
    "architect": null,
    "constructor": null,
    "description": "جزیره شمالی در بخش بندر ریگ شهرستان گناوه به‌عنوان یکی از روستاهای هدف گردشگری استان بوشهر معرفی شده است."
  },
  {
    "name": "قلعه و تپهٔ ریشهر",
    "images": [
      "https://upload.wikimedia.org/wikipedia/commons/c/c1/Rishehr_bay.jpg"
    ],
    "year_built": null,
    "architect": null,
    "constructor": null,
    "description": "آثار باقی‌مانده از قلعه و تپهٔ ریشهر مربوط به دورهٔ ایلامی در بندر بوشهر."
  },
  {
    "name": "گوردختر",
    "images": ["https://commons.wikimedia.org/wiki/Special:FilePath/Gur_Dokhtar1.jpg"],
    "year_built": null,
    "architect": null,
    "constructor": null,
    "description": "گور دختر مربوط به دورهٔ هخامنشی در شهرستان دشتستان."
  },
  {
    "name": "کاخ بردک سیاه و محوطهٔ سعدآباد",
    "images": ["https://upload.wikimedia.org/wikipedia/commons/a/ae/%D8%B4%D9%87%D8%B1_%D8%A8%D8%A7%D8%B3%D8%AA%D8%A7%D9%86%DB%8C_%D8%AA%D9%85%D9%88%DA%A9%D9%8E%D9%86_%28%D8%A8%D8%B1%D8%AF%DA%A9_%D8%B3%DB%8C%D8%A7%D9%87_%D8%AF%D9%88%D8%B1%D8%AF%DA%AF%D8%A7%D9%87%29.jpg"],
    "year_built": null,
    "architect": null,
    "constructor": null,
    "description": "کاخ بردک سیاه و محوطهٔ باستانی سعدآباد مربوط به دورهٔ ساسانی در شهرستان دشتستان."
  },
  {
    "name": "قبور پالمیریان",
    "images": ["https://upload.wikimedia.org/wikipedia/commons/4/44/%D9%85%D8%B3%D8%AC%D8%AF_%D9%88_%D9%82%D8%A8%D9%88%D8%B1_%D9%BE%D8%A7%D9%84%D9%85%DB%8C%D8%B1%DB%8C%D8%A7%D9%86-%D9%86%D9%85%D8%A7%D9%87%D8%A7%DB%8C_%DA%AF%D9%88%D9%86%D8%A7%DA%AF%D9%88%D9%86_%D8%A2%D8%AB%D8%A7%D8%B1_%D8%AA%D9%85%D8%AF%D9%86_%D8%AA%D8%AF%D9%85%D8%B1_%D9%88_%D9%BE%D8%A7%D9%84%D9%85%DB%8C%D8%B1_%D9%85%D8%B1%D8%A8%D9%88%D8%B7_%D8%A8%D9%87_%D8%AF%D9%88%D8%B1%D9%87_%D8%A7%D8%B4%DA%A9%D8%A7%D9%86%DB%8C%D8%A7%D9%86_07.jpg"],
    "year_built": null,
    "architect": null,
    "constructor": null,
    "description": "قبور پالمیریان مربوط به دورهٔ ساسانی در جزیرهٔ خارک."
  },
  {
    "name": "نیایشگاه مُند",
    "images": ["https://www.alaedin.travel/Files/Jazebe/dashti/kalat-temple-in-dashti/Alaedin-Travel-Agency-Attraction-Kalat-Temple-Dashti-1.jpg"],
    "year_built": null,
    "architect": null,
    "constructor": null,
    "description": "نیایشگاه مُند مربوط به دورهٔ ساسانی در منطقهٔ خورموج، شهرستان دشتی."
  },
  {
    "name": "کوشک اردشیر",
    "images": ["https://fa.wikipedia.org/wiki/%DA%A9%D9%88%D8%B4%DA%A9_%D8%A7%D8%B1%D8%AF%D8%B4%DB%8C%D8%B1#/media/%D9%BE%D8%B1%D9%88%D9%86%D8%AF%D9%87:Koreh_Ardeshir.jpg"],
    "year_built": null,
    "architect": null,
    "constructor": null,
    "description": "کوشک اردشیر مربوط به دورهٔ ساسانی در شهرستان دشتستان."
  },
  {
    "name": "خرابه‌های بندر سیراف",
    "images": [
      "https://last-cdn.com/2018/06/13/kA98CDfRg8RGSYM2bpflvDMWcftGIVVmqk4dXibX.jpeg",
      "https://last-cdn.com/2018/06/13/nT4iqIVF559xpWuGsxR7DKVg6ozOcb8VXgMAfex9.jpeg"
    ],
    "year_built": null,
    "architect": null,
    "constructor": null,
    "description": "خرابه‌های بندر سیراف مربوط به دورهٔ ساسانی ــ اسلامی در شهرستان کنگان. شهر با عظمت و پرشکوه سیراف سرانجام در زلزله هولناکی که در نیمه دوم قرن چهارم هجری رخ داد به کلی ویران شد و بخش قابل توجهی از آن نیز به زیر آب فرو رفت. اکنون از آن همه شکوه، تنها ستون های نیمه فرو ریخته، دیوارهای شکسته، قبرهای متروک و مساجد ویران باقی مانده است."
  },
  {
    "name": "تل گوری و پناهگاه مال قائد",
    "images": ["https://api2.kojaro.com/media/2024-2-2187091d-ddab-4673-92aa-bcc4ae50411c-67c46117c1067c5ba768a4da?w=1200&q=80"],
    "year_built": null,
    "architect": null,
    "constructor": null,
    "description": "تل گوری و پناهگاه مال قائد مربوط به دورهٔ ساسانی در شهرستان گناوه."
  }
  ],
  "additional_info": {
    "books_source": "http://chap.sch.ir/category/دوره-آموزش-متوسطه/جغرافیای-استان‌ها",
    "online_resources": [
            "https://fa.wikipedia.org/wiki/استان_بوشهر",
            "https://fa.wikipedia.org/wiki/گردشگری_در_بوشهر",
            "https://ostb.ir/",
            "https://www.chtn.ir/news/1402120800367/%D8%AC%D8%A7%D9%87%D8%A8%D9%87-%D9%87%D8%A7%DB%8C-%DA%AF%D8%B1%D8%AF%D8%B4%DA%AF%D8%B1%DB%8C-%D8%AA%D8%A7%D8%B1%DB%8C%D8%AE%DB%8C-%D9%88-%D8%B7%D8%A8%DB%8C%D8%B9%DB%8C-%D8%A7%D8%B3%D8%AA%D8%A7%D9%86-%D8%A8%D9%88%D8%B4%D9%87%D8%B1",
            "https://www.kojaro.com/bandar-bushehr/",
            "https://www.kojaro.com/bushehr/",
            "https://www.alibaba.ir/mag/bushehr/bushehr-ci/travel-to-bushehr-province/",
            "https://www.karnaval.ir/things-to-do/list-bushehr-province",
            "https://www.eghamat24.com/blog/31336/bushehr-attractions",
            "https://safarmarket.com/blog/attractions/iran/bushehr/bushehr-attractions",
            "https://seeiran.ir/tag/%D8%AC%D8%A7%D9%87%D8%A7%DB%8C-%D8%AF%DB%8C%D8%AF%D9%86%DB%8C-%D8%A8%D9%88%D8%B4%D9%87%D8%B1/",
            "https://seeiran.ir/category/states/boshehr/",
            "https://seeiran.ir/%D8%AC%D8%A7%D9%87%D8%A7%DB%8C-%D8%AF%DB%8C%D8%AF%D9%86%DB%8C-%D8%A8%D9%88%D8%B4%D9%87%D8%B1-%D8%AF%D8%B1-%D8%B2%D9%85%D8%B3%D8%AA%D8%A7%D9%86/",
            "https://seeiran.ir/%D8%AC%D8%A7%D9%87%D8%A7%DB%8C-%D9%87%D8%A7%DB%8C-%D8%AA%D8%A7%D8%B1%DB%8C%D8%AE%DB%8C-%D8%A8%D9%88%D8%B4%D9%87%D8%B1/",
            "https://seeiran.ir/tag/%D8%AC%D8%A7%D9%87%DB%8C-%D8%AA%D8%A7%D8%B1%DB%8C%D8%AE%DB%8C-%D8%A8%D9%88%D8%B4%D9%87%D8%B1/",
            "https://mirasbushehr.ir/",
            "https://www.eghamat24.com/blog/31336/bushehr-attractions",
            "https://www.eligasht.com/Blog/tourism/%D8%AC%D8%A7%D8%B0%D8%A8%D9%87-%D9%87%D8%A7%DB%8C-%D8%A8%D9%88%D8%B4%D9%87%D8%B1/",
            "https://www.iranhotelonline.com/blog/post-1564/%D8%AC%D8%A7%D9%87%D8%A7%DB%8C-%D8%AF%DB%8C%D8%AF%D9%86%DB%8C-%D8%A8%D9%88%D8%B4%D9%87%D8%B1-%D8%A8%D8%A7-%D8%B9%DA%A9%D8%B3-%D9%88-%D8%A2%D8%AF%D8%B1%D8%B3/"
    ]
  }
}